{
    "modelData": {
        "fileType": "graph",
        "repoService": "Unknown",
        "repo": "",
        "filePath": "/Users/james/working/update-logical-graphs/../daliuge-logical-graphs/SDP PIP Pipelines/MS-MSF_Ti-Fq-Fc-Sb.json",
        "sha": "",
        "git_url": ""
    },
    "nodeDataArray": [
        {
            "category": "Memory",
            "categoryType": "Data",
            "isData": false,
            "isGroup": false,
            "canHaveInputs": true,
            "canHaveOutputs": true,
            "color": "#394BB2",
            "drawOrderHint": 0,
            "key": -24,
            "text": "full observation Image",
            "description": "",
            "x": 1126,
            "y": 436,
            "width": 200,
            "height": 200,
            "collapsed": false,
            "showPorts": false,
            "streaming": false,
            "subject": null,
            "selected": false,
            "expanded": false,
            "group": -20,
            "inputApplicationName": "",
            "outputApplicationName": "",
            "exitApplicationName": "",
            "inputApplicationType": "None",
            "outputApplicationType": "None",
            "exitApplicationType": "None",
            "inputPorts": [
                {
                    "Id": "66407a58-48b4-408d-9a15-c37ab690622a",
                    "IdText": "T-B"
                }
            ],
            "outputPorts": [
                {
                    "Id": "25fb8cb9-e33d-4a63-b514-7b2808dd41c6",
                    "IdText": "R-R"
                }
            ],
            "inputLocalPorts": [],
            "outputLocalPorts": [],
            "inputAppFields": [],
            "outputAppFields": [],
            "fields": []
        },
        {
            "category": "Start",
            "categoryType": "Control",
            "isData": false,
            "isGroup": false,
            "canHaveInputs": false,
            "canHaveOutputs": true,
            "color": "#229954",
            "drawOrderHint": 0,
            "key": -27,
            "text": "Start",
            "description": "",
            "x": 300,
            "y": 178,
            "width": 200,
            "height": 200,
            "collapsed": false,
            "showPorts": false,
            "streaming": false,
            "subject": null,
            "selected": false,
            "expanded": false,
            "inputApplicationName": "",
            "outputApplicationName": "",
            "exitApplicationName": "",
            "inputApplicationType": "None",
            "outputApplicationType": "None",
            "exitApplicationType": "None",
            "inputPorts": [],
            "outputPorts": [
                {
                    "Id": "209d47b6-6d36-4086-b790-bd23987b00a3",
                    "IdText": "B-L"
                }
            ],
            "inputLocalPorts": [],
            "outputLocalPorts": [],
            "inputAppFields": [],
            "outputAppFields": [],
            "fields": []
        },
        {
            "category": "Comment",
            "categoryType": "Other",
            "isData": false,
            "isGroup": false,
            "canHaveInputs": false,
            "canHaveOutputs": false,
            "color": "#799938",
            "drawOrderHint": 0,
            "key": -60,
            "text": "",
            "description": "",
            "x": 1462,
            "y": 405,
            "width": 200,
            "height": 200,
            "collapsed": false,
            "showPorts": false,
            "streaming": false,
            "subject": null,
            "selected": false,
            "expanded": false,
            "inputApplicationName": "",
            "outputApplicationName": "",
            "exitApplicationName": "",
            "inputApplicationType": "None",
            "outputApplicationType": "None",
            "exitApplicationType": "None",
            "inputPorts": [],
            "outputPorts": [],
            "inputLocalPorts": [],
            "outputLocalPorts": [],
            "inputAppFields": [],
            "outputAppFields": [],
            "fields": [
                {
                    "text": "Comment",
                    "name": "comment",
                    "value": "Place to look at the data quantities. We will explore the number of drops in this frame work.",
                    "description": "The text value of the comment"
                }
            ]
        },
        {
            "category": "Component",
            "categoryType": "Application",
            "isData": false,
            "isGroup": false,
            "canHaveInputs": true,
            "canHaveOutputs": true,
            "color": "#3498DB",
            "drawOrderHint": 0,
            "key": -2,
            "text": "Copy MS",
            "description": "",
            "x": 386,
            "y": 260,
            "width": 200,
            "height": 200,
            "collapsed": false,
            "showPorts": false,
            "streaming": false,
            "subject": null,
            "selected": false,
            "expanded": false,
            "inputApplicationName": "",
            "outputApplicationName": "",
            "exitApplicationName": "",
            "inputApplicationType": "None",
            "outputApplicationType": "None",
            "exitApplicationType": "None",
            "inputPorts": [
                {
                    "Id": "4abe1948-8853-45f7-a2c5-afb2a14b0e5f",
                    "IdText": "B-L"
                }
            ],
            "outputPorts": [
                {
                    "Id": "1819394e-9382-4119-b9b2-94221c8030fe",
                    "IdText": "B-T"
                }
            ],
            "inputLocalPorts": [],
            "outputLocalPorts": [],
            "inputAppFields": [],
            "outputAppFields": [],
            "fields": []
        },
        {
            "category": "Memory",
            "categoryType": "Data",
            "isData": false,
            "isGroup": false,
            "canHaveInputs": true,
            "canHaveOutputs": true,
            "color": "#394BB2",
            "drawOrderHint": 0,
            "key": -3,
            "text": "Local MS",
            "description": "",
            "x": 386,
            "y": 325,
            "width": 200,
            "height": 200,
            "collapsed": false,
            "showPorts": false,
            "streaming": false,
            "subject": null,
            "selected": false,
            "expanded": false,
            "inputApplicationName": "",
            "outputApplicationName": "",
            "exitApplicationName": "",
            "inputApplicationType": "None",
            "outputApplicationType": "None",
            "exitApplicationType": "None",
            "inputPorts": [
                {
                    "Id": "328b62f6-eced-46b2-997f-b0bb10aa5c06",
                    "IdText": "B-T"
                }
            ],
            "outputPorts": [
                {
                    "Id": "a1109c9e-ae30-4ed6-9bd0-8abd0b4c8d8c",
                    "IdText": "B-T"
                }
            ],
            "inputLocalPorts": [],
            "outputLocalPorts": [],
            "inputAppFields": [],
            "outputAppFields": [],
            "fields": []
        },
        {
            "category": "Component",
            "categoryType": "Application",
            "isData": false,
            "isGroup": false,
            "canHaveInputs": true,
            "canHaveOutputs": true,
            "color": "#3498DB",
            "drawOrderHint": 0,
            "key": -5,
            "text": "split on subband",
            "description": "",
            "x": 387,
            "y": 465,
            "width": 200,
            "height": 200,
            "collapsed": false,
            "showPorts": false,
            "streaming": false,
            "subject": null,
            "selected": false,
            "expanded": false,
            "inputApplicationName": "",
            "outputApplicationName": "",
            "exitApplicationName": "",
            "inputApplicationType": "None",
            "outputApplicationType": "None",
            "exitApplicationType": "None",
            "inputPorts": [
                {
                    "Id": "8a5b81d8-8bcd-4383-acbe-b9c3df20f4e4",
                    "IdText": "B-T"
                }
            ],
            "outputPorts": [
                {
                    "Id": "801b870a-366a-4b2e-b1e3-26ff3e228095",
                    "IdText": "R-L"
                }
            ],
            "inputLocalPorts": [],
            "outputLocalPorts": [],
            "inputAppFields": [],
            "outputAppFields": [],
            "fields": []
        },
        {
            "category": "Scatter",
            "categoryType": "Group",
            "isData": false,
            "isGroup": true,
            "canHaveInputs": true,
            "canHaveOutputs": true,
            "color": "#DDAD00",
            "drawOrderHint": 0,
            "key": -8,
            "text": "Scatter Snapshot",
            "description": "",
            "x": 929,
            "y": 520,
            "width": 200,
            "height": 200,
            "collapsed": false,
            "showPorts": false,
            "streaming": false,
            "subject": null,
            "selected": false,
            "expanded": false,
            "inputApplicationName": "",
            "outputApplicationName": "",
            "exitApplicationName": "",
            "inputApplicationType": "None",
            "outputApplicationType": "None",
            "exitApplicationType": "None",
            "inputPorts": [],
            "outputPorts": [],
            "inputLocalPorts": [],
            "outputLocalPorts": [],
            "inputAppFields": [],
            "outputAppFields": [],
            "fields": [
                {
                    "text": "Number of copies",
                    "name": "num_of_copies",
                    "value": "1",
                    "description": ""
                },
                {
                    "text": "Scatter Axis",
                    "name": "scatter_axis",
                    "value": "",
                    "description": ""
                }
            ]
        },
        {
            "category": "Component",
            "categoryType": "Application",
            "isData": false,
            "isGroup": false,
            "canHaveInputs": true,
            "canHaveOutputs": true,
            "color": "#3498DB",
            "drawOrderHint": 0,
            "key": -48,
            "text": "DuplicateTransfer",
            "description": "",
            "x": 846,
            "y": 223,
            "width": 200,
            "height": 200,
            "collapsed": false,
            "showPorts": false,
            "streaming": false,
            "subject": null,
            "selected": false,
            "expanded": false,
            "group": -8,
            "inputApplicationName": "",
            "outputApplicationName": "",
            "exitApplicationName": "",
            "inputApplicationType": "None",
            "outputApplicationType": "None",
            "exitApplicationType": "None",
            "inputPorts": [
                {
                    "Id": "acd43011-27d9-493f-be5f-f9f983256e89",
                    "IdText": "B-L"
                }
            ],
            "outputPorts": [
                {
                    "Id": "f52e3202-1526-4515-9766-41c16f58ed0a",
                    "IdText": "B-L"
                }
            ],
            "inputLocalPorts": [],
            "outputLocalPorts": [],
            "inputAppFields": [],
            "outputAppFields": [],
            "fields": []
        },
        {
            "category": "Memory",
            "categoryType": "Data",
            "isData": false,
            "isGroup": false,
            "canHaveInputs": true,
            "canHaveOutputs": true,
            "color": "#394BB2",
            "drawOrderHint": 0,
            "key": -38,
            "text": "Split ephermeral",
            "description": "",
            "x": 676,
            "y": 223,
            "width": 200,
            "height": 200,
            "collapsed": false,
            "showPorts": false,
            "streaming": false,
            "subject": null,
            "selected": false,
            "expanded": false,
            "group": -8,
            "inputApplicationName": "",
            "outputApplicationName": "",
            "exitApplicationName": "",
            "inputApplicationType": "None",
            "outputApplicationType": "None",
            "exitApplicationType": "None",
            "inputPorts": [
                {
                    "Id": "c60dbc42-cfa3-495c-beee-48777d46747b",
                    "IdText": "R-L"
                }
            ],
            "outputPorts": [
                {
                    "Id": "6a4b15ed-4584-44d5-97a1-dec1ec99ec5c",
                    "IdText": "B-L"
                }
            ],
            "inputLocalPorts": [],
            "outputLocalPorts": [],
            "inputAppFields": [],
            "outputAppFields": [],
            "fields": []
        },
        {
            "category": "Scatter",
            "categoryType": "Group",
            "isData": false,
            "isGroup": true,
            "canHaveInputs": true,
            "canHaveOutputs": true,
            "color": "#DDAD00",
            "drawOrderHint": 0,
            "key": -20,
            "text": "Scatter Sub-band",
            "description": "",
            "x": 916,
            "y": 620,
            "width": 200,
            "height": 200,
            "collapsed": false,
            "showPorts": false,
            "streaming": false,
            "subject": null,
            "selected": false,
            "expanded": false,
            "group": -8,
            "inputApplicationName": "",
            "outputApplicationName": "",
            "exitApplicationName": "",
            "inputApplicationType": "None",
            "outputApplicationType": "None",
            "exitApplicationType": "None",
            "inputPorts": [],
            "outputPorts": [],
            "inputLocalPorts": [],
            "outputLocalPorts": [],
            "inputAppFields": [],
            "outputAppFields": [],
            "fields": [
                {
                    "text": "Number of copies",
                    "name": "num_of_copies",
                    "value": "1",
                    "description": ""
                },
                {
                    "text": "Scatter Axis",
                    "name": "scatter_axis",
                    "value": "",
                    "description": ""
                }
            ]
        },
        {
            "category": "Scatter",
            "categoryType": "Group",
            "isData": false,
            "isGroup": true,
            "canHaveInputs": true,
            "canHaveOutputs": true,
            "color": "#DDAD00",
            "drawOrderHint": 0,
            "key": -13,
            "text": "Scatter by Facet",
            "description": "",
            "x": 829,
            "y": 667,
            "width": 200,
            "height": 200,
            "collapsed": false,
            "showPorts": false,
            "streaming": false,
            "subject": null,
            "selected": false,
            "expanded": false,
            "group": -20,
            "inputApplicationName": "",
            "outputApplicationName": "",
            "exitApplicationName": "",
            "inputApplicationType": "None",
            "outputApplicationType": "None",
            "exitApplicationType": "None",
            "inputPorts": [],
            "outputPorts": [],
            "inputLocalPorts": [],
            "outputLocalPorts": [],
            "inputAppFields": [],
            "outputAppFields": [],
            "fields": [
                {
                    "text": "Number of copies",
                    "name": "num_of_copies",
                    "value": "1",
                    "description": ""
                },
                {
                    "text": "Scatter Axis",
                    "name": "scatter_axis",
                    "value": "",
                    "description": ""
                }
            ]
        },
        {
            "category": "Memory",
            "categoryType": "Data",
            "isData": false,
            "isGroup": false,
            "canHaveInputs": true,
            "canHaveOutputs": true,
            "color": "#394BB2",
            "drawOrderHint": 0,
            "key": -26,
            "text": "Rotated Data",
            "description": "",
            "x": 680,
            "y": 525,
            "width": 200,
            "height": 200,
            "collapsed": false,
            "showPorts": false,
            "streaming": false,
            "subject": null,
            "selected": false,
            "expanded": false,
            "group": -13,
            "inputApplicationName": "",
            "outputApplicationName": "",
            "exitApplicationName": "",
            "inputApplicationType": "None",
            "outputApplicationType": "None",
            "exitApplicationType": "None",
            "inputPorts": [
                {
                    "Id": "04521f7f-d291-415c-b0e6-18caa72c1eb2",
                    "IdText": "L-R"
                }
            ],
            "outputPorts": [
                {
                    "Id": "788b7346-6f50-4778-8b8a-3035f1505180",
                    "IdText": "B-T"
                }
            ],
            "inputLocalPorts": [],
            "outputLocalPorts": [],
            "inputAppFields": [],
            "outputAppFields": [],
            "fields": []
        },
        {
            "category": "Component",
            "categoryType": "Application",
            "isData": false,
            "isGroup": false,
            "canHaveInputs": true,
            "canHaveOutputs": true,
            "color": "#3498DB",
            "drawOrderHint": 0,
            "key": -30,
            "text": "Major Cycle\nPredict",
            "description": "",
            "x": 664,
            "y": 615,
            "width": 200,
            "height": 200,
            "collapsed": false,
            "showPorts": false,
            "streaming": false,
            "subject": null,
            "selected": false,
            "expanded": false,
            "group": -13,
            "inputApplicationName": "",
            "outputApplicationName": "",
            "exitApplicationName": "",
            "inputApplicationType": "None",
            "outputApplicationType": "None",
            "exitApplicationType": "None",
            "inputPorts": [
                {
                    "Id": "5d182cbd-15e1-4c01-9a94-2b7ad07b2fa5",
                    "IdText": "B-T"
                },
                {
                    "Id": "46973aa3-29d9-4298-97e6-516e62bef430",
                    "IdText": "R-L"
                }
            ],
            "outputPorts": [
                {
                    "Id": "3c061a69-621a-49e3-b0c3-f755485df25f",
                    "IdText": "R-T"
                }
            ],
            "inputLocalPorts": [],
            "outputLocalPorts": [],
            "inputAppFields": [],
            "outputAppFields": [],
            "fields": []
        },
        {
            "category": "Memory",
            "categoryType": "Data",
            "isData": false,
            "isGroup": false,
            "canHaveInputs": true,
            "canHaveOutputs": true,
            "color": "#394BB2",
            "drawOrderHint": 0,
            "key": -4,
            "text": "uv Subtracted",
            "description": "",
            "x": 976,
            "y": 578,
            "width": 200,
            "height": 200,
            "collapsed": false,
            "showPorts": false,
            "streaming": false,
            "subject": null,
            "selected": false,
            "expanded": false,
            "group": -13,
            "inputApplicationName": "",
            "outputApplicationName": "",
            "exitApplicationName": "",
            "inputApplicationType": "None",
            "outputApplicationType": "None",
            "exitApplicationType": "None",
            "inputPorts": [
                {
                    "Id": "3ba40a13-805b-46ed-bf64-44dafb2aaf6d",
                    "IdText": "R-T"
                }
            ],
            "outputPorts": [
                {
                    "Id": "a6e78476-f700-43b0-a5c3-f0fdc48f9c28",
                    "IdText": "B-T"
                }
            ],
            "inputLocalPorts": [],
            "outputLocalPorts": [],
            "inputAppFields": [],
            "outputAppFields": [],
            "fields": []
        },
        {
            "category": "Component",
            "categoryType": "Application",
            "isData": false,
            "isGroup": false,
            "canHaveInputs": true,
            "canHaveOutputs": true,
            "color": "#3498DB",
            "drawOrderHint": 0,
            "key": -34,
            "text": "Make Image",
            "description": "",
            "x": 1005,
            "y": 755,
            "width": 200,
            "height": 200,
            "collapsed": false,
            "showPorts": false,
            "streaming": false,
            "subject": null,
            "selected": false,
            "expanded": false,
            "group": -13,
            "inputApplicationName": "",
            "outputApplicationName": "",
            "exitApplicationName": "",
            "inputApplicationType": "None",
            "outputApplicationType": "None",
            "exitApplicationType": "None",
            "inputPorts": [
                {
                    "Id": "a65f399c-82fb-4d3c-baf1-cfe723f71d60",
                    "IdText": "B-T"
                }
            ],
            "outputPorts": [
                {
                    "Id": "d02b6562-b4d9-45a0-9347-85f92851aaf9",
                    "IdText": "B-T"
                }
            ],
            "inputLocalPorts": [],
            "outputLocalPorts": [],
            "inputAppFields": [],
            "outputAppFields": [],
            "fields": []
        },
        {
            "category": "Memory",
            "categoryType": "Data",
            "isData": false,
            "isGroup": false,
            "canHaveInputs": true,
            "canHaveOutputs": true,
            "color": "#394BB2",
            "drawOrderHint": 0,
            "key": -35,
            "text": "Dirty Image",
            "description": "",
            "x": 856,
            "y": 746,
            "width": 200,
            "height": 200,
            "collapsed": false,
            "showPorts": false,
            "streaming": false,
            "subject": null,
            "selected": false,
            "expanded": false,
            "group": -13,
            "inputApplicationName": "",
            "outputApplicationName": "",
            "exitApplicationName": "",
            "inputApplicationType": "None",
            "outputApplicationType": "None",
            "exitApplicationType": "None",
            "inputPorts": [
                {
                    "Id": "1a5dedf9-6cad-4fd1-8631-cd6077022fb7",
                    "IdText": "B-T"
                }
            ],
            "outputPorts": [
                {
                    "Id": "d4059ecb-9f66-425b-a06e-ef1ad20fb55d",
                    "IdText": "B-T"
                }
            ],
            "inputLocalPorts": [],
            "outputLocalPorts": [],
            "inputAppFields": [],
            "outputAppFields": [],
            "fields": []
        },
        {
            "category": "Component",
            "categoryType": "Application",
            "isData": false,
            "isGroup": false,
            "canHaveInputs": true,
            "canHaveOutputs": true,
            "color": "#3498DB",
            "drawOrderHint": 0,
            "key": -36,
            "text": "Minor Search and Subtract Loop",
            "description": "",
            "x": 670,
            "y": 748,
            "width": 200,
            "height": 200,
            "collapsed": false,
            "showPorts": false,
            "streaming": false,
            "subject": null,
            "selected": false,
            "expanded": false,
            "group": -13,
            "inputApplicationName": "",
            "outputApplicationName": "",
            "exitApplicationName": "",
            "inputApplicationType": "None",
            "outputApplicationType": "None",
            "exitApplicationType": "None",
            "inputPorts": [
                {
                    "Id": "bf1625bf-0a6e-40df-b9e6-bb85bf49ad26",
                    "IdText": "B-T"
                }
            ],
            "outputPorts": [
                {
                    "Id": "a9bf587a-d0eb-4131-8aee-692bb0f644cd",
                    "IdText": "B-T"
                }
            ],
            "inputLocalPorts": [],
            "outputLocalPorts": [],
            "inputAppFields": [],
            "outputAppFields": [],
            "fields": []
        },
        {
            "category": "Memory",
            "categoryType": "Data",
            "isData": false,
            "isGroup": false,
            "canHaveInputs": true,
            "canHaveOutputs": true,
            "color": "#394BB2",
            "drawOrderHint": 0,
            "key": -42,
            "text": "New Delta Model",
            "description": "",
            "x": 727,
            "y": 810,
            "width": 200,
            "height": 200,
            "collapsed": false,
            "showPorts": false,
            "streaming": false,
            "subject": null,
            "selected": false,
            "expanded": false,
            "group": -13,
            "inputApplicationName": "",
            "outputApplicationName": "",
            "exitApplicationName": "",
            "inputApplicationType": "None",
            "outputApplicationType": "None",
            "exitApplicationType": "None",
            "inputPorts": [
                {
                    "Id": "74c093e8-fa19-42a6-9d7c-6e0f8536eef7",
                    "IdText": "B-T"
                }
            ],
            "outputPorts": [
                {
                    "Id": "2059a606-35b6-4d16-aa25-048e2a4bbb15",
                    "IdText": "B-L"
                }
            ],
            "inputLocalPorts": [],
            "outputLocalPorts": [],
            "inputAppFields": [],
            "outputAppFields": [],
            "fields": []
        },
        {
            "category": "Unknown",
            "categoryType": "Unknown",
            "isData": false,
            "isGroup": false,
            "canHaveInputs": false,
            "canHaveOutputs": false,
            "color": "#FF66CC",
            "drawOrderHint": 0,
            "key": -7,
            "text": "Branch\nCondition",
            "description": "",
            "x": 821,
            "y": 655,
            "width": 200,
            "height": 200,
            "collapsed": false,
            "showPorts": false,
            "streaming": false,
            "subject": null,
            "selected": false,
            "expanded": false,
            "group": -13,
            "inputApplicationName": "",
            "outputApplicationName": "",
            "exitApplicationName": "",
            "inputApplicationType": "None",
            "outputApplicationType": "None",
            "exitApplicationType": "None",
            "inputPorts": [
                {
                    "Id": "64be9645-41f5-4abb-b708-9dc5566d5033",
                    "IdText": "B-T"
                }
            ],
            "outputPorts": [
                {
                    "Id": "b88de772-1a4f-49d2-9978-9221c9ccc8ab",
                    "IdText": "B-T"
                },
                {
                    "Id": "5532c639-bdd1-4179-9268-f07fdd2931be",
                    "IdText": "R-L"
                }
            ],
            "inputLocalPorts": [],
            "outputLocalPorts": [],
            "inputAppFields": [],
            "outputAppFields": [],
            "fields": []
        },
        {
            "category": "Memory",
            "categoryType": "Data",
            "isData": false,
            "isGroup": false,
            "canHaveInputs": true,
            "canHaveOutputs": true,
            "color": "#394BB2",
            "drawOrderHint": 0,
            "key": -40,
            "text": "Split ephermeral",
            "description": "",
            "x": 918,
            "y": 424,
            "width": 200,
            "height": 200,
            "collapsed": false,
            "showPorts": false,
            "streaming": false,
            "subject": null,
            "selected": false,
            "expanded": false,
            "group": -20,
            "inputApplicationName": "",
            "outputApplicationName": "",
            "exitApplicationName": "",
            "inputApplicationType": "None",
            "outputApplicationType": "None",
            "exitApplicationType": "None",
            "inputPorts": [
                {
                    "Id": "782a2b7c-a6d5-48f4-9f6c-c1ee76f10daf",
                    "IdText": "B-L"
                }
            ],
            "outputPorts": [
                {
                    "Id": "5d166812-dc79-44ec-b9dd-b0498cadee8f",
                    "IdText": "B-T"
                }
            ],
            "inputLocalPorts": [],
            "outputLocalPorts": [],
            "inputAppFields": [],
            "outputAppFields": [],
            "fields": []
        },
        {
            "category": "Component",
            "categoryType": "Application",
            "isData": false,
            "isGroup": false,
            "canHaveInputs": true,
            "canHaveOutputs": true,
            "color": "#3498DB",
            "drawOrderHint": 0,
            "key": -41,
            "text": "Phase Rotate",
            "description": "",
            "x": 956,
            "y": 524,
            "width": 200,
            "height": 200,
            "collapsed": false,
            "showPorts": false,
            "streaming": false,
            "subject": null,
            "selected": false,
            "expanded": false,
            "group": -13,
            "inputApplicationName": "",
            "outputApplicationName": "",
            "exitApplicationName": "",
            "inputApplicationType": "None",
            "outputApplicationType": "None",
            "exitApplicationType": "None",
            "inputPorts": [
                {
                    "Id": "65e07255-b978-436a-9215-8221d640b416",
                    "IdText": "B-T"
                }
            ],
            "outputPorts": [
                {
                    "Id": "169f9561-1858-4235-8504-0b32bf528b62",
                    "IdText": "L-R"
                }
            ],
            "inputLocalPorts": [],
            "outputLocalPorts": [],
            "inputAppFields": [],
            "outputAppFields": [],
            "fields": []
        },
        {
            "category": "Component",
            "categoryType": "Application",
            "isData": false,
            "isGroup": false,
            "canHaveInputs": true,
            "canHaveOutputs": true,
            "color": "#3498DB",
            "drawOrderHint": 0,
            "key": -37,
            "text": "Feather Facets",
            "description": "",
            "x": 1168,
            "y": 647,
            "width": 200,
            "height": 200,
            "collapsed": false,
            "showPorts": false,
            "streaming": false,
            "subject": null,
            "selected": false,
            "expanded": false,
            "group": -20,
            "inputApplicationName": "",
            "outputApplicationName": "",
            "exitApplicationName": "",
            "inputApplicationType": "None",
            "outputApplicationType": "None",
            "exitApplicationType": "None",
            "inputPorts": [
                {
                    "Id": "ce003132-3aab-47e3-80d6-1a20ecf3f3ab",
                    "IdText": "R-L"
                }
            ],
            "outputPorts": [
                {
                    "Id": "e49cb959-7d4d-455e-8930-a24d0385dc67",
                    "IdText": "T-B"
                }
            ],
            "inputLocalPorts": [],
            "outputLocalPorts": [],
            "inputAppFields": [],
            "outputAppFields": [],
            "fields": []
        },
        {
            "category": "Component",
            "categoryType": "Application",
            "isData": false,
            "isGroup": false,
            "canHaveInputs": true,
            "canHaveOutputs": true,
            "color": "#3498DB",
            "drawOrderHint": 0,
            "key": -25,
            "text": "Concat sube",
            "description": "",
            "x": 1057,
            "y": 307,
            "width": 200,
            "height": 200,
            "collapsed": false,
            "showPorts": false,
            "streaming": false,
            "subject": null,
            "selected": false,
            "expanded": false,
            "group": -8,
            "inputApplicationName": "",
            "outputApplicationName": "",
            "exitApplicationName": "",
            "inputApplicationType": "None",
            "outputApplicationType": "None",
            "exitApplicationType": "None",
            "inputPorts": [
                {
                    "Id": "3afbde9e-5829-4889-acc3-1f2a95a27cc4",
                    "IdText": "R-R"
                }
            ],
            "outputPorts": [
                {
                    "Id": "c352cfe7-cfbe-4316-94f3-be3741a84146",
                    "IdText": "T-B"
                }
            ],
            "inputLocalPorts": [],
            "outputLocalPorts": [],
            "inputAppFields": [],
            "outputAppFields": [],
            "fields": []
        },
        {
            "category": "Memory",
            "categoryType": "Data",
            "isData": false,
            "isGroup": false,
            "canHaveInputs": true,
            "canHaveOutputs": true,
            "color": "#394BB2",
            "drawOrderHint": 0,
            "key": -28,
            "text": "Full FoV subband image",
            "description": "",
            "x": 1057,
            "y": 225,
            "width": 200,
            "height": 200,
            "collapsed": false,
            "showPorts": false,
            "streaming": false,
            "subject": null,
            "selected": false,
            "expanded": false,
            "group": -8,
            "inputApplicationName": "",
            "outputApplicationName": "",
            "exitApplicationName": "",
            "inputApplicationType": "None",
            "outputApplicationType": "None",
            "exitApplicationType": "None",
            "inputPorts": [
                {
                    "Id": "21a69bb0-58bc-4b06-a1e0-ed9abc8b7bb6",
                    "IdText": "T-B"
                }
            ],
            "outputPorts": [
                {
                    "Id": "8d3cc0dd-8fb5-4e1e-b162-34733a6b896b",
                    "IdText": "T-B"
                }
            ],
            "inputLocalPorts": [],
            "outputLocalPorts": [],
            "inputAppFields": [],
            "outputAppFields": [],
            "fields": []
        },
        {
            "category": "Comment",
            "categoryType": "Other",
            "isData": false,
            "isGroup": false,
            "canHaveInputs": false,
            "canHaveOutputs": false,
            "color": "#799938",
            "drawOrderHint": 0,
            "key": -55,
            "text": "",
            "description": "",
            "x": 757,
            "y": 101,
            "width": 200,
            "height": 200,
            "collapsed": false,
            "showPorts": false,
            "streaming": false,
            "subject": null,
            "selected": false,
            "expanded": false,
            "inputApplicationName": "",
            "outputApplicationName": "",
            "exitApplicationName": "",
            "inputApplicationType": "None",
            "outputApplicationType": "None",
            "exitApplicationType": "None",
            "inputPorts": [],
            "outputPorts": [],
            "inputLocalPorts": [],
            "outputLocalPorts": [],
            "inputAppFields": [],
            "outputAppFields": [],
            "fields": [
                {
                    "text": "Comment",
                    "name": "comment",
                    "value": "Work in progress --- too much copied over from other graphs!",
                    "description": "The text value of the comment"
                }
            ]
        },
        {
            "category": "End",
            "categoryType": "Control",
            "isData": false,
            "isGroup": false,
            "canHaveInputs": true,
            "canHaveOutputs": false,
            "color": "#CB4335",
            "drawOrderHint": 0,
            "key": -10,
            "text": "End",
            "description": "",
            "x": 1509,
            "y": 203,
            "width": 200,
            "height": 200,
            "collapsed": false,
            "showPorts": false,
            "streaming": false,
            "subject": null,
            "selected": false,
            "expanded": false,
            "inputApplicationName": "",
            "outputApplicationName": "",
            "exitApplicationName": "",
            "inputApplicationType": "None",
            "outputApplicationType": "None",
            "exitApplicationType": "None",
            "inputPorts": [
                {
                    "Id": "561a8c92-3f5b-43c5-9daa-5cadfcb4e514",
                    "IdText": "B-T"
                }
            ],
            "outputPorts": [],
            "inputLocalPorts": [],
            "outputLocalPorts": [],
            "inputAppFields": [],
            "outputAppFields": [],
            "fields": []
        },
        {
            "category": "Component",
            "categoryType": "Application",
            "isData": false,
            "isGroup": false,
            "canHaveInputs": true,
            "canHaveOutputs": true,
            "color": "#3498DB",
            "drawOrderHint": 0,
            "key": -29,
            "text": "Combine Snapshots",
            "description": "",
            "x": 1130,
            "y": 100,
            "width": 200,
            "height": 200,
            "collapsed": false,
            "showPorts": false,
            "streaming": false,
            "subject": null,
            "selected": false,
            "expanded": false,
            "inputApplicationName": "",
            "outputApplicationName": "",
            "exitApplicationName": "",
            "inputApplicationType": "None",
            "outputApplicationType": "None",
            "exitApplicationType": "None",
            "inputPorts": [
                {
                    "Id": "e4b0b540-fed7-490e-9e3f-71717f3f72fa",
                    "IdText": "T-B"
                }
            ],
            "outputPorts": [
                {
                    "Id": "146a5f00-8529-4a96-b67c-fddf66aa6b34",
                    "IdText": "R-L"
                }
            ],
            "inputLocalPorts": [],
            "outputLocalPorts": [],
            "inputAppFields": [],
            "outputAppFields": [],
            "fields": []
        },
        {
            "category": "Memory",
            "categoryType": "Data",
            "isData": false,
            "isGroup": false,
            "canHaveInputs": true,
            "canHaveOutputs": true,
            "color": "#394BB2",
            "drawOrderHint": 0,
            "key": -31,
            "text": "Full FoV Full image",
            "description": "",
            "x": 1324,
            "y": 109,
            "width": 200,
            "height": 200,
            "collapsed": false,
            "showPorts": false,
            "streaming": false,
            "subject": null,
            "selected": false,
            "expanded": false,
            "inputApplicationName": "",
            "outputApplicationName": "",
            "exitApplicationName": "",
            "inputApplicationType": "None",
            "outputApplicationType": "None",
            "exitApplicationType": "None",
            "inputPorts": [
                {
                    "Id": "04f4d912-4578-4498-a6f6-ac73a70bef03",
                    "IdText": "R-L"
                }
            ],
            "outputPorts": [
                {
                    "Id": "29e3d1bf-d408-4bee-b034-75f49fd55d38",
                    "IdText": "B-T"
                }
            ],
            "inputLocalPorts": [],
            "outputLocalPorts": [],
            "inputAppFields": [],
            "outputAppFields": [],
            "fields": []
        },
        {
            "category": "Memory",
            "categoryType": "Data",
            "isData": false,
            "isGroup": false,
            "canHaveInputs": true,
            "canHaveOutputs": true,
            "color": "#394BB2",
            "drawOrderHint": 0,
            "key": -11,
            "text": "LSM",
            "description": "",
            "x": 320,
            "y": 583,
            "width": 200,
            "height": 200,
            "collapsed": false,
            "showPorts": false,
            "streaming": false,
            "subject": null,
            "selected": false,
            "expanded": false,
            "inputApplicationName": "",
            "outputApplicationName": "",
            "exitApplicationName": "",
            "inputApplicationType": "None",
            "outputApplicationType": "None",
            "exitApplicationType": "None",
            "inputPorts": [],
            "outputPorts": [
                {
                    "Id": "ba0f2ef8-9b16-4c81-ad04-1757a39ecb6c",
                    "IdText": "R-L"
                }
            ],
            "inputLocalPorts": [],
            "outputLocalPorts": [],
            "inputAppFields": [],
            "outputAppFields": [],
            "fields": []
        },
        {
            "category": "Component",
            "categoryType": "Application",
            "isData": false,
            "isGroup": false,
            "canHaveInputs": true,
            "canHaveOutputs": true,
            "color": "#3498DB",
            "drawOrderHint": 0,
            "key": -32,
            "text": "Update model",
            "description": "",
            "x": 351,
            "y": 658,
            "width": 200,
            "height": 200,
            "collapsed": false,
            "showPorts": false,
            "streaming": false,
            "subject": null,
            "selected": false,
            "expanded": false,
            "inputApplicationName": "",
            "outputApplicationName": "",
            "exitApplicationName": "",
            "inputApplicationType": "None",
            "outputApplicationType": "None",
            "exitApplicationType": "None",
            "inputPorts": [
                {
                    "Id": "4a10baa1-08c6-4c8c-b823-2d8104ed7b9f",
                    "IdText": "B-L"
                }
            ],
            "outputPorts": [],
            "inputLocalPorts": [],
            "outputLocalPorts": [],
            "inputAppFields": [],
            "outputAppFields": [],
            "fields": []
        }
    ],
    "linkDataArray": [
        {
            "from": -27,
            "fromPort": "209d47b6-6d36-4086-b790-bd23987b00a3",
            "to": -2,
            "toPort": "4abe1948-8853-45f7-a2c5-afb2a14b0e5f"
        },
        {
            "from": -2,
            "fromPort": "1819394e-9382-4119-b9b2-94221c8030fe",
            "to": -3,
            "toPort": "328b62f6-eced-46b2-997f-b0bb10aa5c06"
        },
        {
            "from": -3,
            "fromPort": "a1109c9e-ae30-4ed6-9bd0-8abd0b4c8d8c",
            "to": -5,
            "toPort": "8a5b81d8-8bcd-4383-acbe-b9c3df20f4e4"
        },
        {
            "from": -30,
            "fromPort": "3c061a69-621a-49e3-b0c3-f755485df25f",
            "to": -4,
            "toPort": "3ba40a13-805b-46ed-bf64-44dafb2aaf6d"
        },
        {
            "from": -34,
            "fromPort": "d02b6562-b4d9-45a0-9347-85f92851aaf9",
            "to": -35,
            "toPort": "1a5dedf9-6cad-4fd1-8631-cd6077022fb7"
        },
        {
            "from": -35,
            "fromPort": "d4059ecb-9f66-425b-a06e-ef1ad20fb55d",
            "to": -36,
            "toPort": "bf1625bf-0a6e-40df-b9e6-bb85bf49ad26"
        },
        {
            "from": -36,
            "fromPort": "a9bf587a-d0eb-4131-8aee-692bb0f644cd",
            "to": -42,
            "toPort": "74c093e8-fa19-42a6-9d7c-6e0f8536eef7"
        },
        {
            "from": -4,
            "fromPort": "a6e78476-f700-43b0-a5c3-f0fdc48f9c28",
            "to": -7,
            "toPort": "64be9645-41f5-4abb-b708-9dc5566d5033"
        },
        {
            "from": -7,
            "fromPort": "b88de772-1a4f-49d2-9978-9221c9ccc8ab",
            "to": -34,
            "toPort": "a65f399c-82fb-4d3c-baf1-cfe723f71d60"
        },
        {
            "from": -26,
            "fromPort": "788b7346-6f50-4778-8b8a-3035f1505180",
            "to": -30,
            "toPort": "5d182cbd-15e1-4c01-9a94-2b7ad07b2fa5"
        },
        {
            "from": -41,
            "fromPort": "169f9561-1858-4235-8504-0b32bf528b62",
            "to": -26,
            "toPort": "04521f7f-d291-415c-b0e6-18caa72c1eb2"
        },
        {
            "from": -7,
            "fromPort": "5532c639-bdd1-4179-9268-f07fdd2931be",
            "to": -37,
            "toPort": "ce003132-3aab-47e3-80d6-1a20ecf3f3ab"
        },
        {
            "from": -37,
            "fromPort": "e49cb959-7d4d-455e-8930-a24d0385dc67",
            "to": -24,
            "toPort": "66407a58-48b4-408d-9a15-c37ab690622a"
        },
        {
            "from": -48,
            "fromPort": "f52e3202-1526-4515-9766-41c16f58ed0a",
            "to": -40,
            "toPort": "782a2b7c-a6d5-48f4-9f6c-c1ee76f10daf"
        },
        {
            "from": -38,
            "fromPort": "6a4b15ed-4584-44d5-97a1-dec1ec99ec5c",
            "to": -48,
            "toPort": "acd43011-27d9-493f-be5f-f9f983256e89"
        },
        {
            "from": -24,
            "fromPort": "25fb8cb9-e33d-4a63-b514-7b2808dd41c6",
            "to": -25,
            "toPort": "3afbde9e-5829-4889-acc3-1f2a95a27cc4"
        },
        {
            "from": -25,
            "fromPort": "c352cfe7-cfbe-4316-94f3-be3741a84146",
            "to": -28,
            "toPort": "21a69bb0-58bc-4b06-a1e0-ed9abc8b7bb6"
        },
        {
            "from": -5,
            "fromPort": "801b870a-366a-4b2e-b1e3-26ff3e228095",
            "to": -38,
            "toPort": "c60dbc42-cfa3-495c-beee-48777d46747b"
        },
        {
            "from": -28,
            "fromPort": "8d3cc0dd-8fb5-4e1e-b162-34733a6b896b",
            "to": -29,
            "toPort": "e4b0b540-fed7-490e-9e3f-71717f3f72fa"
        },
        {
            "from": -29,
            "fromPort": "146a5f00-8529-4a96-b67c-fddf66aa6b34",
            "to": -31,
            "toPort": "04f4d912-4578-4498-a6f6-ac73a70bef03"
        },
        {
            "from": -31,
            "fromPort": "29e3d1bf-d408-4bee-b034-75f49fd55d38",
            "to": -10,
            "toPort": "561a8c92-3f5b-43c5-9daa-5cadfcb4e514"
        },
        {
            "from": -11,
            "fromPort": "ba0f2ef8-9b16-4c81-ad04-1757a39ecb6c",
            "to": -30,
            "toPort": "46973aa3-29d9-4298-97e6-516e62bef430"
        },
        {
            "from": -42,
            "fromPort": "2059a606-35b6-4d16-aa25-048e2a4bbb15",
            "to": -32,
            "toPort": "4a10baa1-08c6-4c8c-b823-2d8104ed7b9f"
        },
        {
            "from": -40,
            "fromPort": "5d166812-dc79-44ec-b9dd-b0498cadee8f",
            "to": -41,
            "toPort": "65e07255-b978-436a-9215-8221d640b416"
        }
    ]
}