{
    "modelData": {
        "fileType": "graph",
        "repoService": "Unknown",
        "repo": "",
        "filePath": "/Users/james/working/update-logical-graphs/../daliuge-logical-graphs/SDP Pipelines/facet_img.json",
        "sha": "",
        "git_url": ""
    },
    "nodeDataArray": [
        {
            "category": "Scatter",
            "categoryType": "Group",
            "isData": false,
            "isGroup": true,
            "canHaveInputs": true,
            "canHaveOutputs": true,
            "color": "#DDAD00",
            "drawOrderHint": 0,
            "key": -8,
            "text": "Scatter Subband",
            "description": "",
            "x": 805,
            "y": 781,
            "width": 200,
            "height": 200,
            "collapsed": false,
            "showPorts": false,
            "streaming": false,
            "subject": null,
            "selected": false,
            "expanded": false,
            "group": -9,
            "inputApplicationName": "",
            "outputApplicationName": "",
            "exitApplicationName": "",
            "inputApplicationType": "None",
            "outputApplicationType": "None",
            "exitApplicationType": "None",
            "inputPorts": [],
            "outputPorts": [],
            "inputLocalPorts": [],
            "outputLocalPorts": [],
            "inputAppFields": [],
            "outputAppFields": [],
            "fields": [
                {
                    "text": "Number of copies",
                    "name": "num_of_copies",
                    "value": "1",
                    "description": ""
                },
                {
                    "text": "Scatter Axis",
                    "name": "scatter_axis",
                    "value": "",
                    "description": ""
                }
            ]
        },
        {
            "category": "Scatter",
            "categoryType": "Group",
            "isData": false,
            "isGroup": true,
            "canHaveInputs": true,
            "canHaveOutputs": true,
            "color": "#DDAD00",
            "drawOrderHint": 0,
            "key": -20,
            "text": "Scatter Facet",
            "description": "",
            "x": 813,
            "y": 942,
            "width": 200,
            "height": 200,
            "collapsed": false,
            "showPorts": false,
            "streaming": false,
            "subject": null,
            "selected": false,
            "expanded": false,
            "group": -8,
            "inputApplicationName": "",
            "outputApplicationName": "",
            "exitApplicationName": "",
            "inputApplicationType": "None",
            "outputApplicationType": "None",
            "exitApplicationType": "None",
            "inputPorts": [],
            "outputPorts": [],
            "inputLocalPorts": [],
            "outputLocalPorts": [],
            "inputAppFields": [],
            "outputAppFields": [],
            "fields": [
                {
                    "text": "Number of copies",
                    "name": "num_of_copies",
                    "value": "1",
                    "description": ""
                },
                {
                    "text": "Scatter Axis",
                    "name": "scatter_axis",
                    "value": "",
                    "description": ""
                }
            ]
        },
        {
            "category": "Component",
            "categoryType": "Application",
            "isData": false,
            "isGroup": false,
            "canHaveInputs": true,
            "canHaveOutputs": true,
            "color": "#3498DB",
            "drawOrderHint": 0,
            "key": -19,
            "text": "predict",
            "description": "",
            "x": 657,
            "y": 888,
            "width": 200,
            "height": 200,
            "collapsed": false,
            "showPorts": false,
            "streaming": false,
            "subject": null,
            "selected": false,
            "expanded": false,
            "group": -20,
            "inputApplicationName": "",
            "outputApplicationName": "",
            "exitApplicationName": "",
            "inputApplicationType": "None",
            "outputApplicationType": "None",
            "exitApplicationType": "None",
            "inputPorts": [
                {
                    "Id": "42bdb179-d669-4a37-a923-d318e04653da",
                    "IdText": "B-T"
                },
                {
                    "Id": "3ff89eac-10a7-4781-a423-a2fe977a013e",
                    "IdText": "<default>-<default>"
                }
            ],
            "outputPorts": [
                {
                    "Id": "eb180926-b220-47b5-bfc4-789cdfd47507",
                    "IdText": "R-L"
                }
            ],
            "inputLocalPorts": [],
            "outputLocalPorts": [],
            "inputAppFields": [],
            "outputAppFields": [],
            "fields": []
        },
        {
            "category": "Component",
            "categoryType": "Application",
            "isData": false,
            "isGroup": false,
            "canHaveInputs": true,
            "canHaveOutputs": true,
            "color": "#3498DB",
            "drawOrderHint": 0,
            "key": -22,
            "text": "Solve",
            "description": "",
            "x": 981,
            "y": 966,
            "width": 200,
            "height": 200,
            "collapsed": false,
            "showPorts": false,
            "streaming": false,
            "subject": null,
            "selected": false,
            "expanded": false,
            "group": -20,
            "inputApplicationName": "",
            "outputApplicationName": "",
            "exitApplicationName": "",
            "inputApplicationType": "None",
            "outputApplicationType": "None",
            "exitApplicationType": "None",
            "inputPorts": [
                {
                    "Id": "573ddd59-f17c-497f-9531-709306944c0d",
                    "IdText": "R-T"
                }
            ],
            "outputPorts": [
                {
                    "Id": "6530a415-9dab-48a9-bb34-ed12cb5f8bcf",
                    "IdText": "B-R"
                }
            ],
            "inputLocalPorts": [],
            "outputLocalPorts": [],
            "inputAppFields": [],
            "outputAppFields": [],
            "fields": []
        },
        {
            "category": "Component",
            "categoryType": "Application",
            "isData": false,
            "isGroup": false,
            "canHaveInputs": true,
            "canHaveOutputs": true,
            "color": "#3498DB",
            "drawOrderHint": 0,
            "key": -23,
            "text": "Apply",
            "description": "",
            "x": 648,
            "y": 1002,
            "width": 200,
            "height": 200,
            "collapsed": false,
            "showPorts": false,
            "streaming": false,
            "subject": null,
            "selected": false,
            "expanded": false,
            "group": -20,
            "inputApplicationName": "",
            "outputApplicationName": "",
            "exitApplicationName": "",
            "inputApplicationType": "None",
            "outputApplicationType": "None",
            "exitApplicationType": "None",
            "inputPorts": [
                {
                    "Id": "9a18f403-c27f-48e5-8d08-793c6323cd26",
                    "IdText": "L-R"
                },
                {
                    "Id": "c250f06b-8a0f-4ed4-ae21-e4bf23030aae",
                    "IdText": "L-T"
                },
                {
                    "Id": "829bbb17-7e48-4e6a-94ab-371eade864fe",
                    "IdText": "R-L"
                }
            ],
            "outputPorts": [
                {
                    "Id": "6ceb3641-54ea-4829-a516-bffa9e90db55",
                    "IdText": "B-T"
                }
            ],
            "inputLocalPorts": [],
            "outputLocalPorts": [],
            "inputAppFields": [],
            "outputAppFields": [],
            "fields": []
        },
        {
            "category": "Component",
            "categoryType": "Application",
            "isData": false,
            "isGroup": false,
            "canHaveInputs": true,
            "canHaveOutputs": true,
            "color": "#3498DB",
            "drawOrderHint": 0,
            "key": -24,
            "text": "Subtract",
            "description": "",
            "x": 740,
            "y": 1129,
            "width": 200,
            "height": 200,
            "collapsed": false,
            "showPorts": false,
            "streaming": false,
            "subject": null,
            "selected": false,
            "expanded": false,
            "group": -20,
            "inputApplicationName": "",
            "outputApplicationName": "",
            "exitApplicationName": "",
            "inputApplicationType": "None",
            "outputApplicationType": "None",
            "exitApplicationType": "None",
            "inputPorts": [
                {
                    "Id": "707d994c-5799-4da5-a45d-c5965dc7a6b7",
                    "IdText": "B-L"
                }
            ],
            "outputPorts": [
                {
                    "Id": "4bedb5fa-819c-4595-889a-14dd08ce05c2",
                    "IdText": "R-L"
                }
            ],
            "inputLocalPorts": [],
            "outputLocalPorts": [],
            "inputAppFields": [],
            "outputAppFields": [],
            "fields": []
        },
        {
            "category": "Memory",
            "categoryType": "Data",
            "isData": false,
            "isGroup": false,
            "canHaveInputs": true,
            "canHaveOutputs": true,
            "color": "#394BB2",
            "drawOrderHint": 0,
            "key": -25,
            "text": "Update\nDDE Gains",
            "description": "",
            "x": 893,
            "y": 1002,
            "width": 200,
            "height": 200,
            "collapsed": false,
            "showPorts": false,
            "streaming": false,
            "subject": null,
            "selected": false,
            "expanded": false,
            "group": -20,
            "inputApplicationName": "",
            "outputApplicationName": "",
            "exitApplicationName": "",
            "inputApplicationType": "None",
            "outputApplicationType": "None",
            "exitApplicationType": "None",
            "inputPorts": [
                {
                    "Id": "7206f669-064b-4625-94de-7782663aa060",
                    "IdText": "B-R"
                }
            ],
            "outputPorts": [
                {
                    "Id": "56bfb1e9-c2f4-4c42-b8fa-95ef0c8ce952",
                    "IdText": "L-R"
                }
            ],
            "inputLocalPorts": [],
            "outputLocalPorts": [],
            "inputAppFields": [],
            "outputAppFields": [],
            "fields": []
        },
        {
            "category": "Memory",
            "categoryType": "Data",
            "isData": false,
            "isGroup": false,
            "canHaveInputs": true,
            "canHaveOutputs": true,
            "color": "#394BB2",
            "drawOrderHint": 0,
            "key": -26,
            "text": "Rotated Data",
            "description": "",
            "x": 657,
            "y": 802,
            "width": 200,
            "height": 200,
            "collapsed": false,
            "showPorts": false,
            "streaming": false,
            "subject": null,
            "selected": false,
            "expanded": false,
            "group": -20,
            "inputApplicationName": "",
            "outputApplicationName": "",
            "exitApplicationName": "",
            "inputApplicationType": "None",
            "outputApplicationType": "None",
            "exitApplicationType": "None",
            "inputPorts": [
                {
                    "Id": "543ae37b-8bf0-4309-96f0-88e57f8ad67a",
                    "IdText": "L-R"
                }
            ],
            "outputPorts": [
                {
                    "Id": "aadcb9b2-a522-4600-95dd-72c515291280",
                    "IdText": "B-T"
                }
            ],
            "inputLocalPorts": [],
            "outputLocalPorts": [],
            "inputAppFields": [],
            "outputAppFields": [],
            "fields": []
        },
        {
            "category": "Unknown",
            "categoryType": "Unknown",
            "isData": false,
            "isGroup": false,
            "canHaveInputs": false,
            "canHaveOutputs": false,
            "color": "#FF66CC",
            "drawOrderHint": 0,
            "key": -31,
            "text": "Sufficient\nflux",
            "description": "",
            "x": 840,
            "y": 928,
            "width": 200,
            "height": 200,
            "collapsed": false,
            "showPorts": false,
            "streaming": false,
            "subject": null,
            "selected": false,
            "expanded": false,
            "group": -20,
            "inputApplicationName": "",
            "outputApplicationName": "",
            "exitApplicationName": "",
            "inputApplicationType": "None",
            "outputApplicationType": "None",
            "exitApplicationType": "None",
            "inputPorts": [
                {
                    "Id": "dd4d0ffe-f42e-4f24-9f6c-43a2530f7576",
                    "IdText": "B-T"
                }
            ],
            "outputPorts": [
                {
                    "Id": "33c08a20-d1bb-4c70-b8e6-c0549227e56c",
                    "IdText": "R-T"
                },
                {
                    "Id": "4c60aec6-45fd-4c63-b118-7c1585523f16",
                    "IdText": "L-T"
                }
            ],
            "inputLocalPorts": [],
            "outputLocalPorts": [],
            "inputAppFields": [],
            "outputAppFields": [],
            "fields": []
        },
        {
            "category": "Memory",
            "categoryType": "Data",
            "isData": false,
            "isGroup": false,
            "canHaveInputs": true,
            "canHaveOutputs": true,
            "color": "#394BB2",
            "drawOrderHint": 0,
            "key": -30,
            "text": "Calibrated Data",
            "description": "",
            "x": 648,
            "y": 1069,
            "width": 200,
            "height": 200,
            "collapsed": false,
            "showPorts": false,
            "streaming": false,
            "subject": null,
            "selected": false,
            "expanded": false,
            "group": -20,
            "inputApplicationName": "",
            "outputApplicationName": "",
            "exitApplicationName": "",
            "inputApplicationType": "None",
            "outputApplicationType": "None",
            "exitApplicationType": "None",
            "inputPorts": [
                {
                    "Id": "c0f3a2fd-ad74-456f-9363-8839e6b9bb8d",
                    "IdText": "B-T"
                }
            ],
            "outputPorts": [
                {
                    "Id": "e0a78bb7-3714-4e37-9103-1da2c6eef46f",
                    "IdText": "B-L"
                }
            ],
            "inputLocalPorts": [],
            "outputLocalPorts": [],
            "inputAppFields": [],
            "outputAppFields": [],
            "fields": []
        },
        {
            "category": "Memory",
            "categoryType": "Data",
            "isData": false,
            "isGroup": false,
            "canHaveInputs": true,
            "canHaveOutputs": true,
            "color": "#394BB2",
            "drawOrderHint": 0,
            "key": -33,
            "text": "Subtracted Data",
            "description": "",
            "x": 921,
            "y": 1129,
            "width": 200,
            "height": 200,
            "collapsed": false,
            "showPorts": false,
            "streaming": false,
            "subject": null,
            "selected": false,
            "expanded": false,
            "group": -20,
            "inputApplicationName": "",
            "outputApplicationName": "",
            "exitApplicationName": "",
            "inputApplicationType": "None",
            "outputApplicationType": "None",
            "exitApplicationType": "None",
            "inputPorts": [
                {
                    "Id": "fe53fefd-cf27-4004-ab9a-3ce80a45ce24",
                    "IdText": "R-L"
                }
            ],
            "outputPorts": [
                {
                    "Id": "a19f49ef-9d52-4974-8525-b78c8cb72c75",
                    "IdText": "T-R"
                },
                {
                    "Id": "94b57bdb-d84b-4ad7-9a1f-83f2b20e8c7f",
                    "IdText": "R-T"
                }
            ],
            "inputLocalPorts": [],
            "outputLocalPorts": [],
            "inputAppFields": [],
            "outputAppFields": [],
            "fields": []
        },
        {
            "category": "Memory",
            "categoryType": "Data",
            "isData": false,
            "isGroup": false,
            "canHaveInputs": true,
            "canHaveOutputs": true,
            "color": "#394BB2",
            "drawOrderHint": 0,
            "key": -36,
            "text": "Modelled Data",
            "description": "",
            "x": 840,
            "y": 839,
            "width": 200,
            "height": 200,
            "collapsed": false,
            "showPorts": false,
            "streaming": false,
            "subject": null,
            "selected": false,
            "expanded": false,
            "group": -20,
            "inputApplicationName": "",
            "outputApplicationName": "",
            "exitApplicationName": "",
            "inputApplicationType": "None",
            "outputApplicationType": "None",
            "exitApplicationType": "None",
            "inputPorts": [
                {
                    "Id": "df33d41d-7af2-4c17-95f6-7c00cd2b399b",
                    "IdText": "R-L"
                }
            ],
            "outputPorts": [
                {
                    "Id": "023f6598-38f7-4552-a2db-26a41fe67793",
                    "IdText": "B-T"
                }
            ],
            "inputLocalPorts": [],
            "outputLocalPorts": [],
            "inputAppFields": [],
            "outputAppFields": [],
            "fields": []
        },
        {
            "category": "Memory",
            "categoryType": "Data",
            "isData": false,
            "isGroup": false,
            "canHaveInputs": true,
            "canHaveOutputs": true,
            "color": "#394BB2",
            "drawOrderHint": 0,
            "key": -40,
            "text": "Split ephermeral",
            "description": "",
            "x": 938,
            "y": 753,
            "width": 200,
            "height": 200,
            "collapsed": false,
            "showPorts": false,
            "streaming": false,
            "subject": null,
            "selected": false,
            "expanded": false,
            "group": -20,
            "inputApplicationName": "",
            "outputApplicationName": "",
            "exitApplicationName": "",
            "inputApplicationType": "None",
            "outputApplicationType": "None",
            "exitApplicationType": "None",
            "inputPorts": [
                {
                    "Id": "fd05f294-e1bd-466e-9f4f-ece71b48a05d",
                    "IdText": "B-L"
                }
            ],
            "outputPorts": [
                {
                    "Id": "7ed4e7eb-5177-4522-b897-ebfef2fc3de7",
                    "IdText": "B-R"
                }
            ],
            "inputLocalPorts": [],
            "outputLocalPorts": [],
            "inputAppFields": [],
            "outputAppFields": [],
            "fields": []
        },
        {
            "category": "Component",
            "categoryType": "Application",
            "isData": false,
            "isGroup": false,
            "canHaveInputs": true,
            "canHaveOutputs": true,
            "color": "#3498DB",
            "drawOrderHint": 0,
            "key": -41,
            "text": "Phase Rotate",
            "description": "",
            "x": 862,
            "y": 802,
            "width": 200,
            "height": 200,
            "collapsed": false,
            "showPorts": false,
            "streaming": false,
            "subject": null,
            "selected": false,
            "expanded": false,
            "group": -20,
            "inputApplicationName": "",
            "outputApplicationName": "",
            "exitApplicationName": "",
            "inputApplicationType": "None",
            "outputApplicationType": "None",
            "exitApplicationType": "None",
            "inputPorts": [
                {
                    "Id": "520a2196-2f14-4c8a-a5b3-0e5c2eb2018b",
                    "IdText": "B-R"
                }
            ],
            "outputPorts": [
                {
                    "Id": "4b5645e9-82e9-4730-83a3-d200ebd44369",
                    "IdText": "L-R"
                }
            ],
            "inputLocalPorts": [],
            "outputLocalPorts": [],
            "inputAppFields": [],
            "outputAppFields": [],
            "fields": []
        },
        {
            "category": "Component",
            "categoryType": "Application",
            "isData": false,
            "isGroup": false,
            "canHaveInputs": true,
            "canHaveOutputs": true,
            "color": "#3498DB",
            "drawOrderHint": 0,
            "key": -46,
            "text": "DQA3",
            "description": "",
            "x": 880,
            "y": 1089,
            "width": 200,
            "height": 200,
            "collapsed": false,
            "showPorts": false,
            "streaming": false,
            "subject": null,
            "selected": false,
            "expanded": false,
            "group": -20,
            "inputApplicationName": "",
            "outputApplicationName": "",
            "exitApplicationName": "",
            "inputApplicationType": "None",
            "outputApplicationType": "None",
            "exitApplicationType": "None",
            "inputPorts": [
                {
                    "Id": "3c40ecee-15a1-4875-9149-549dc9d93eb7",
                    "IdText": "T-R"
                }
            ],
            "outputPorts": [
                {
                    "Id": "9ce794e0-3910-4f7b-bc04-4fda0852fa7c",
                    "IdText": "L-B"
                }
            ],
            "inputLocalPorts": [],
            "outputLocalPorts": [],
            "inputAppFields": [],
            "outputAppFields": [],
            "fields": []
        },
        {
            "category": "Memory",
            "categoryType": "Data",
            "isData": false,
            "isGroup": false,
            "canHaveInputs": true,
            "canHaveOutputs": true,
            "color": "#394BB2",
            "drawOrderHint": 0,
            "key": -47,
            "text": "Resid Image",
            "description": "",
            "x": 797,
            "y": 1051,
            "width": 200,
            "height": 200,
            "collapsed": false,
            "showPorts": false,
            "streaming": false,
            "subject": null,
            "selected": false,
            "expanded": false,
            "group": -20,
            "inputApplicationName": "",
            "outputApplicationName": "",
            "exitApplicationName": "",
            "inputApplicationType": "None",
            "outputApplicationType": "None",
            "exitApplicationType": "None",
            "inputPorts": [
                {
                    "Id": "c099f2fb-aff1-470e-8cab-5fceea0e147e",
                    "IdText": "L-B"
                }
            ],
            "outputPorts": [
                {
                    "Id": "2681bcec-02eb-4455-ba41-89db4148fe4d",
                    "IdText": "R-L"
                }
            ],
            "inputLocalPorts": [],
            "outputLocalPorts": [],
            "inputAppFields": [],
            "outputAppFields": [],
            "fields": []
        },
        {
            "category": "Component",
            "categoryType": "Application",
            "isData": false,
            "isGroup": false,
            "canHaveInputs": true,
            "canHaveOutputs": true,
            "color": "#3498DB",
            "drawOrderHint": 0,
            "key": -52,
            "text": "Assessment for \nDQA3",
            "description": "",
            "x": 996,
            "y": 1051,
            "width": 200,
            "height": 200,
            "collapsed": false,
            "showPorts": false,
            "streaming": false,
            "subject": null,
            "selected": false,
            "expanded": false,
            "group": -20,
            "inputApplicationName": "",
            "outputApplicationName": "",
            "exitApplicationName": "",
            "inputApplicationType": "None",
            "outputApplicationType": "None",
            "exitApplicationType": "None",
            "inputPorts": [
                {
                    "Id": "14ef7119-530b-439d-ae4d-4672303353d3",
                    "IdText": "R-L"
                }
            ],
            "outputPorts": [
                {
                    "Id": "c3ef48a9-ca32-471c-8b46-6fd3c3cd11a5",
                    "IdText": "R-B"
                }
            ],
            "inputLocalPorts": [],
            "outputLocalPorts": [],
            "inputAppFields": [],
            "outputAppFields": [],
            "fields": []
        },
        {
            "category": "Memory",
            "categoryType": "Data",
            "isData": false,
            "isGroup": false,
            "canHaveInputs": true,
            "canHaveOutputs": true,
            "color": "#394BB2",
            "drawOrderHint": 0,
            "key": -38,
            "text": "Split ephermeral",
            "description": "",
            "x": 773,
            "y": 426,
            "width": 200,
            "height": 200,
            "collapsed": false,
            "showPorts": false,
            "streaming": false,
            "subject": null,
            "selected": false,
            "expanded": false,
            "group": -8,
            "inputApplicationName": "",
            "outputApplicationName": "",
            "exitApplicationName": "",
            "inputApplicationType": "None",
            "outputApplicationType": "None",
            "exitApplicationType": "None",
            "inputPorts": [
                {
                    "Id": "3d88a9e4-7a5a-4a72-a787-fab11946fb15",
                    "IdText": "B-R"
                }
            ],
            "outputPorts": [
                {
                    "Id": "89cc2860-3056-4564-b935-60c155c8190e",
                    "IdText": "B-T"
                },
                {
                    "Id": "3dfe8fb4-0baf-405f-8634-9520f8a573d7",
                    "IdText": "B-T"
                }
            ],
            "inputLocalPorts": [],
            "outputLocalPorts": [],
            "inputAppFields": [],
            "outputAppFields": [],
            "fields": []
        },
        {
            "category": "Component",
            "categoryType": "Application",
            "isData": false,
            "isGroup": false,
            "canHaveInputs": true,
            "canHaveOutputs": true,
            "color": "#3498DB",
            "drawOrderHint": 0,
            "key": -44,
            "text": "Process for DQA2",
            "description": "",
            "x": 960,
            "y": 484,
            "width": 200,
            "height": 200,
            "collapsed": false,
            "showPorts": false,
            "streaming": false,
            "subject": null,
            "selected": false,
            "expanded": false,
            "group": -8,
            "inputApplicationName": "",
            "outputApplicationName": "",
            "exitApplicationName": "",
            "inputApplicationType": "None",
            "outputApplicationType": "None",
            "exitApplicationType": "None",
            "inputPorts": [
                {
                    "Id": "ea40f507-667d-4a5b-979e-614dae226dc4",
                    "IdText": "B-T"
                }
            ],
            "outputPorts": [
                {
                    "Id": "2e431728-6b0a-43df-ba21-b20214c6ae2f",
                    "IdText": "B-T"
                }
            ],
            "inputLocalPorts": [],
            "outputLocalPorts": [],
            "inputAppFields": [],
            "outputAppFields": [],
            "fields": []
        },
        {
            "category": "Memory",
            "categoryType": "Data",
            "isData": false,
            "isGroup": false,
            "canHaveInputs": true,
            "canHaveOutputs": true,
            "color": "#394BB2",
            "drawOrderHint": 0,
            "key": -45,
            "text": "Cont Image",
            "description": "",
            "x": 962,
            "y": 539,
            "width": 200,
            "height": 200,
            "collapsed": false,
            "showPorts": false,
            "streaming": false,
            "subject": null,
            "selected": false,
            "expanded": false,
            "group": -8,
            "inputApplicationName": "",
            "outputApplicationName": "",
            "exitApplicationName": "",
            "inputApplicationType": "None",
            "outputApplicationType": "None",
            "exitApplicationType": "None",
            "inputPorts": [
                {
                    "Id": "6e60b195-7d68-4cbd-ba5c-716e30a78156",
                    "IdText": "B-T"
                }
            ],
            "outputPorts": [
                {
                    "Id": "d8c1b5cc-6d09-427b-91a9-1dc6e6b05af9",
                    "IdText": "L-R"
                }
            ],
            "inputLocalPorts": [],
            "outputLocalPorts": [],
            "inputAppFields": [],
            "outputAppFields": [],
            "fields": []
        },
        {
            "category": "Component",
            "categoryType": "Application",
            "isData": false,
            "isGroup": false,
            "canHaveInputs": true,
            "canHaveOutputs": true,
            "color": "#3498DB",
            "drawOrderHint": 0,
            "key": -48,
            "text": "DuplicateTransfer",
            "description": "",
            "x": 653,
            "y": 557,
            "width": 200,
            "height": 200,
            "collapsed": false,
            "showPorts": false,
            "streaming": false,
            "subject": null,
            "selected": false,
            "expanded": false,
            "group": -8,
            "inputApplicationName": "",
            "outputApplicationName": "",
            "exitApplicationName": "",
            "inputApplicationType": "None",
            "outputApplicationType": "None",
            "exitApplicationType": "None",
            "inputPorts": [
                {
                    "Id": "71b84463-33ea-4070-864d-e398cddea6d2",
                    "IdText": "B-T"
                }
            ],
            "outputPorts": [
                {
                    "Id": "321d9bf0-b925-43f2-8fdb-3685b7cd6bcd",
                    "IdText": "B-L"
                }
            ],
            "inputLocalPorts": [],
            "outputLocalPorts": [],
            "inputAppFields": [],
            "outputAppFields": [],
            "fields": []
        },
        {
            "category": "Component",
            "categoryType": "Application",
            "isData": false,
            "isGroup": false,
            "canHaveInputs": true,
            "canHaveOutputs": true,
            "color": "#3498DB",
            "drawOrderHint": 0,
            "key": -51,
            "text": "Assessment for \nDQA2",
            "description": "",
            "x": 800,
            "y": 540,
            "width": 200,
            "height": 200,
            "collapsed": false,
            "showPorts": false,
            "streaming": false,
            "subject": null,
            "selected": false,
            "expanded": false,
            "group": -8,
            "inputApplicationName": "",
            "outputApplicationName": "",
            "exitApplicationName": "",
            "inputApplicationType": "None",
            "outputApplicationType": "None",
            "exitApplicationType": "None",
            "inputPorts": [
                {
                    "Id": "661e61a6-74b9-46e4-b473-50cec9ef593b",
                    "IdText": "L-R"
                }
            ],
            "outputPorts": [
                {
                    "Id": "2b700f63-b1ab-4545-a97f-66dd4dcf71f6",
                    "IdText": "B-L"
                }
            ],
            "inputLocalPorts": [],
            "outputLocalPorts": [],
            "inputAppFields": [],
            "outputAppFields": [],
            "fields": []
        },
        {
            "category": "Start",
            "categoryType": "Control",
            "isData": false,
            "isGroup": false,
            "canHaveInputs": false,
            "canHaveOutputs": true,
            "color": "#229954",
            "drawOrderHint": 0,
            "key": -27,
            "text": "Start",
            "description": "",
            "x": 478,
            "y": 274,
            "width": 200,
            "height": 200,
            "collapsed": false,
            "showPorts": false,
            "streaming": false,
            "subject": null,
            "selected": false,
            "expanded": false,
            "inputApplicationName": "",
            "outputApplicationName": "",
            "exitApplicationName": "",
            "inputApplicationType": "None",
            "outputApplicationType": "None",
            "exitApplicationType": "None",
            "inputPorts": [],
            "outputPorts": [
                {
                    "Id": "3d70ba08-38d3-48cb-bd16-f97dcbc562b1",
                    "IdText": "<default>-<default>"
                }
            ],
            "inputLocalPorts": [],
            "outputLocalPorts": [],
            "inputAppFields": [],
            "outputAppFields": [],
            "fields": []
        },
        {
            "category": "Component",
            "categoryType": "Application",
            "isData": false,
            "isGroup": false,
            "canHaveInputs": true,
            "canHaveOutputs": true,
            "color": "#3498DB",
            "drawOrderHint": 0,
            "key": -2,
            "text": "Copy MS",
            "description": "",
            "x": 750,
            "y": 291,
            "width": 200,
            "height": 200,
            "collapsed": false,
            "showPorts": false,
            "streaming": false,
            "subject": null,
            "selected": false,
            "expanded": false,
            "group": -9,
            "inputApplicationName": "",
            "outputApplicationName": "",
            "exitApplicationName": "",
            "inputApplicationType": "None",
            "outputApplicationType": "None",
            "exitApplicationType": "None",
            "inputPorts": [
                {
                    "Id": "91bda289-61d1-46c6-961a-6d19a379cf11",
                    "IdText": "<default>-<default>"
                }
            ],
            "outputPorts": [
                {
                    "Id": "de4c6c15-d342-4d3f-ac61-ec8f04d2f3ed",
                    "IdText": "<default>-<default>"
                }
            ],
            "inputLocalPorts": [],
            "outputLocalPorts": [],
            "inputAppFields": [],
            "outputAppFields": [],
            "fields": []
        },
        {
            "category": "Memory",
            "categoryType": "Data",
            "isData": false,
            "isGroup": false,
            "canHaveInputs": true,
            "canHaveOutputs": true,
            "color": "#394BB2",
            "drawOrderHint": 0,
            "key": -3,
            "text": "MS Per Period",
            "description": "",
            "x": 963,
            "y": 291,
            "width": 200,
            "height": 200,
            "collapsed": false,
            "showPorts": false,
            "streaming": false,
            "subject": null,
            "selected": false,
            "expanded": false,
            "group": -9,
            "inputApplicationName": "",
            "outputApplicationName": "",
            "exitApplicationName": "",
            "inputApplicationType": "None",
            "outputApplicationType": "None",
            "exitApplicationType": "None",
            "inputPorts": [
                {
                    "Id": "ea142eaa-2c29-409c-9851-18b2748d5cb8",
                    "IdText": "<default>-<default>"
                }
            ],
            "outputPorts": [
                {
                    "Id": "5b0ef79a-0256-4e17-ad8e-0641f5ed5688",
                    "IdText": "<default>-<default>"
                },
                {
                    "Id": "1a64618c-952d-43c8-812e-6d6a117e3451",
                    "IdText": "B-T"
                }
            ],
            "inputLocalPorts": [],
            "outputLocalPorts": [],
            "inputAppFields": [],
            "outputAppFields": [],
            "fields": []
        },
        {
            "category": "Component",
            "categoryType": "Application",
            "isData": false,
            "isGroup": false,
            "canHaveInputs": true,
            "canHaveOutputs": true,
            "color": "#3498DB",
            "drawOrderHint": 0,
            "key": -5,
            "text": "split on subband",
            "description": "",
            "x": 1117,
            "y": 291,
            "width": 200,
            "height": 200,
            "collapsed": false,
            "showPorts": false,
            "streaming": false,
            "subject": null,
            "selected": false,
            "expanded": false,
            "group": -9,
            "inputApplicationName": "",
            "outputApplicationName": "",
            "exitApplicationName": "",
            "inputApplicationType": "None",
            "outputApplicationType": "None",
            "exitApplicationType": "None",
            "inputPorts": [
                {
                    "Id": "ae73c259-347c-4a5f-90e4-c3618296dcaf",
                    "IdText": "<default>-<default>"
                }
            ],
            "outputPorts": [
                {
                    "Id": "f743ddd6-f5b6-446c-8e36-3d33d9cac644",
                    "IdText": "B-R"
                }
            ],
            "inputLocalPorts": [],
            "outputLocalPorts": [],
            "inputAppFields": [],
            "outputAppFields": [],
            "fields": []
        },
        {
            "category": "Scatter",
            "categoryType": "Group",
            "isData": false,
            "isGroup": true,
            "canHaveInputs": true,
            "canHaveOutputs": true,
            "color": "#DDAD00",
            "drawOrderHint": 0,
            "key": -9,
            "text": "Scatter Time",
            "description": "",
            "x": 873,
            "y": 717,
            "width": 200,
            "height": 200,
            "collapsed": false,
            "showPorts": false,
            "streaming": false,
            "subject": null,
            "selected": false,
            "expanded": false,
            "inputApplicationName": "",
            "outputApplicationName": "",
            "exitApplicationName": "",
            "inputApplicationType": "None",
            "outputApplicationType": "None",
            "exitApplicationType": "None",
            "inputPorts": [],
            "outputPorts": [],
            "inputLocalPorts": [],
            "outputLocalPorts": [],
            "inputAppFields": [],
            "outputAppFields": [],
            "fields": [
                {
                    "text": "Number of copies",
                    "name": "num_of_copies",
                    "value": "1",
                    "description": ""
                },
                {
                    "text": "Scatter Axis",
                    "name": "scatter_axis",
                    "value": "",
                    "description": ""
                }
            ]
        },
        {
            "category": "Component",
            "categoryType": "Application",
            "isData": false,
            "isGroup": false,
            "canHaveInputs": true,
            "canHaveOutputs": true,
            "color": "#3498DB",
            "drawOrderHint": 0,
            "key": -42,
            "text": "Process for \nDQA1",
            "description": "",
            "x": 1144,
            "y": 423,
            "width": 200,
            "height": 200,
            "collapsed": false,
            "showPorts": false,
            "streaming": false,
            "subject": null,
            "selected": false,
            "expanded": false,
            "group": -9,
            "inputApplicationName": "",
            "outputApplicationName": "",
            "exitApplicationName": "",
            "inputApplicationType": "None",
            "outputApplicationType": "None",
            "exitApplicationType": "None",
            "inputPorts": [
                {
                    "Id": "7a94f78f-b14b-47b9-8ea4-773e10db2720",
                    "IdText": "B-T"
                }
            ],
            "outputPorts": [
                {
                    "Id": "ab4d6336-ae74-497f-abfe-bcdfe533c7d8",
                    "IdText": "B-T"
                }
            ],
            "inputLocalPorts": [],
            "outputLocalPorts": [],
            "inputAppFields": [],
            "outputAppFields": [],
            "fields": []
        },
        {
            "category": "Memory",
            "categoryType": "Data",
            "isData": false,
            "isGroup": false,
            "canHaveInputs": true,
            "canHaveOutputs": true,
            "color": "#394BB2",
            "drawOrderHint": 0,
            "key": -43,
            "text": "Spectra",
            "description": "",
            "x": 1144,
            "y": 501,
            "width": 200,
            "height": 200,
            "collapsed": false,
            "showPorts": false,
            "streaming": false,
            "subject": null,
            "selected": false,
            "expanded": false,
            "group": -9,
            "inputApplicationName": "",
            "outputApplicationName": "",
            "exitApplicationName": "",
            "inputApplicationType": "None",
            "outputApplicationType": "None",
            "exitApplicationType": "None",
            "inputPorts": [
                {
                    "Id": "4f8b0a13-a70d-4394-8602-c7e6d8a3216b",
                    "IdText": "B-T"
                }
            ],
            "outputPorts": [
                {
                    "Id": "3e800c2f-56dd-4f0d-9130-61854a217af6",
                    "IdText": "B-T"
                }
            ],
            "inputLocalPorts": [],
            "outputLocalPorts": [],
            "inputAppFields": [],
            "outputAppFields": [],
            "fields": []
        },
        {
            "category": "Component",
            "categoryType": "Application",
            "isData": false,
            "isGroup": false,
            "canHaveInputs": true,
            "canHaveOutputs": true,
            "color": "#3498DB",
            "drawOrderHint": 0,
            "key": -50,
            "text": "Assessment for \nDQA1",
            "description": "",
            "x": 1145,
            "y": 689,
            "width": 200,
            "height": 200,
            "collapsed": false,
            "showPorts": false,
            "streaming": false,
            "subject": null,
            "selected": false,
            "expanded": false,
            "group": -9,
            "inputApplicationName": "",
            "outputApplicationName": "",
            "exitApplicationName": "",
            "inputApplicationType": "None",
            "outputApplicationType": "None",
            "exitApplicationType": "None",
            "inputPorts": [
                {
                    "Id": "edb4b855-8333-48ff-8b5d-c885e77708b8",
                    "IdText": "B-T"
                }
            ],
            "outputPorts": [
                {
                    "Id": "e99693ca-b957-4dbf-a252-e2987a8785f2",
                    "IdText": "R-R"
                }
            ],
            "inputLocalPorts": [],
            "outputLocalPorts": [],
            "inputAppFields": [],
            "outputAppFields": [],
            "fields": []
        },
        {
            "category": "Memory",
            "categoryType": "Data",
            "isData": false,
            "isGroup": false,
            "canHaveInputs": true,
            "canHaveOutputs": true,
            "color": "#394BB2",
            "drawOrderHint": 0,
            "key": -21,
            "text": "Epoch 1\n(LSM)",
            "description": "",
            "x": 369,
            "y": 821,
            "width": 200,
            "height": 200,
            "collapsed": false,
            "showPorts": false,
            "streaming": false,
            "subject": null,
            "selected": false,
            "expanded": false,
            "inputApplicationName": "",
            "outputApplicationName": "",
            "exitApplicationName": "",
            "inputApplicationType": "None",
            "outputApplicationType": "None",
            "exitApplicationType": "None",
            "inputPorts": [],
            "outputPorts": [
                {
                    "Id": "776b6f14-06b5-47c3-bc7d-d118c49ff7eb",
                    "IdText": "<default>-<default>"
                }
            ],
            "inputLocalPorts": [],
            "outputLocalPorts": [],
            "inputAppFields": [],
            "outputAppFields": [],
            "fields": []
        },
        {
            "category": "Component",
            "categoryType": "Application",
            "isData": false,
            "isGroup": false,
            "canHaveInputs": true,
            "canHaveOutputs": true,
            "color": "#3498DB",
            "drawOrderHint": 0,
            "key": -28,
            "text": "CASA\nFeather",
            "description": "",
            "x": 1477,
            "y": 652,
            "width": 200,
            "height": 200,
            "collapsed": false,
            "showPorts": false,
            "streaming": false,
            "subject": null,
            "selected": false,
            "expanded": false,
            "group": -53,
            "inputApplicationName": "",
            "outputApplicationName": "",
            "exitApplicationName": "",
            "inputApplicationType": "None",
            "outputApplicationType": "None",
            "exitApplicationType": "None",
            "inputPorts": [],
            "outputPorts": [
                {
                    "Id": "8725d727-97ee-46b0-9c37-483d34458524",
                    "IdText": "B-T"
                }
            ],
            "inputLocalPorts": [],
            "outputLocalPorts": [],
            "inputAppFields": [],
            "outputAppFields": [],
            "fields": []
        },
        {
            "category": "Memory",
            "categoryType": "Data",
            "isData": false,
            "isGroup": false,
            "canHaveInputs": true,
            "canHaveOutputs": true,
            "color": "#394BB2",
            "drawOrderHint": 0,
            "key": -29,
            "text": "Full Image \nsub-Cube",
            "description": "",
            "x": 1477,
            "y": 738,
            "width": 200,
            "height": 200,
            "collapsed": false,
            "showPorts": false,
            "streaming": false,
            "subject": null,
            "selected": false,
            "expanded": false,
            "group": -53,
            "inputApplicationName": "",
            "outputApplicationName": "",
            "exitApplicationName": "",
            "inputApplicationType": "None",
            "outputApplicationType": "None",
            "exitApplicationType": "None",
            "inputPorts": [
                {
                    "Id": "d54e0d42-d8d9-41be-bc8b-4e5c97334540",
                    "IdText": "B-T"
                }
            ],
            "outputPorts": [
                {
                    "Id": "2e1d2659-b7e3-4ebd-880f-41f2c8f9b647",
                    "IdText": "B-T"
                }
            ],
            "inputLocalPorts": [],
            "outputLocalPorts": [],
            "inputAppFields": [],
            "outputAppFields": [],
            "fields": []
        },
        {
            "category": "End",
            "categoryType": "Control",
            "isData": false,
            "isGroup": false,
            "canHaveInputs": true,
            "canHaveOutputs": false,
            "color": "#CB4335",
            "drawOrderHint": 0,
            "key": -32,
            "text": "End",
            "description": "",
            "x": 1476,
            "y": 1016,
            "width": 200,
            "height": 200,
            "collapsed": false,
            "showPorts": false,
            "streaming": false,
            "subject": null,
            "selected": false,
            "expanded": false,
            "inputApplicationName": "",
            "outputApplicationName": "",
            "exitApplicationName": "",
            "inputApplicationType": "None",
            "outputApplicationType": "None",
            "exitApplicationType": "None",
            "inputPorts": [
                {
                    "Id": "dc549a78-75f1-472c-ba09-6c172e77757d",
                    "IdText": "B-T"
                }
            ],
            "outputPorts": [],
            "inputLocalPorts": [],
            "outputLocalPorts": [],
            "inputAppFields": [],
            "outputAppFields": [],
            "fields": []
        },
        {
            "category": "Component",
            "categoryType": "Application",
            "isData": false,
            "isGroup": false,
            "canHaveInputs": true,
            "canHaveOutputs": true,
            "color": "#3498DB",
            "drawOrderHint": 0,
            "key": -39,
            "text": "CASA\nConcatenate",
            "description": "",
            "x": 1401,
            "y": 869,
            "width": 200,
            "height": 200,
            "collapsed": false,
            "showPorts": false,
            "streaming": false,
            "subject": null,
            "selected": false,
            "expanded": false,
            "group": -54,
            "inputApplicationName": "",
            "outputApplicationName": "",
            "exitApplicationName": "",
            "inputApplicationType": "None",
            "outputApplicationType": "None",
            "exitApplicationType": "None",
            "inputPorts": [],
            "outputPorts": [
                {
                    "Id": "c545e4a6-22a9-44e6-9c1a-fd45842487c6",
                    "IdText": "B-T"
                }
            ],
            "inputLocalPorts": [],
            "outputLocalPorts": [],
            "inputAppFields": [],
            "outputAppFields": [],
            "fields": []
        },
        {
            "category": "Memory",
            "categoryType": "Data",
            "isData": false,
            "isGroup": false,
            "canHaveInputs": true,
            "canHaveOutputs": true,
            "color": "#394BB2",
            "drawOrderHint": 0,
            "key": -18,
            "text": "Full Image \nCube",
            "description": "",
            "x": 1401,
            "y": 946,
            "width": 200,
            "height": 200,
            "collapsed": false,
            "showPorts": false,
            "streaming": false,
            "subject": null,
            "selected": false,
            "expanded": false,
            "group": -54,
            "inputApplicationName": "",
            "outputApplicationName": "",
            "exitApplicationName": "",
            "inputApplicationType": "None",
            "outputApplicationType": "None",
            "exitApplicationType": "None",
            "inputPorts": [
                {
                    "Id": "7624d0f0-651f-4f38-8faf-295f6cc94453",
                    "IdText": "B-T"
                }
            ],
            "outputPorts": [
                {
                    "Id": "5c93343e-434b-4d60-8dda-c4817f6dd51c",
                    "IdText": "B-T"
                }
            ],
            "inputLocalPorts": [],
            "outputLocalPorts": [],
            "inputAppFields": [],
            "outputAppFields": [],
            "fields": []
        },
        {
            "category": "Component",
            "categoryType": "Application",
            "isData": false,
            "isGroup": false,
            "canHaveInputs": true,
            "canHaveOutputs": true,
            "color": "#3498DB",
            "drawOrderHint": 0,
            "key": -16,
            "text": "CASA Clean",
            "description": "",
            "x": 1349,
            "y": 319,
            "width": 200,
            "height": 200,
            "collapsed": false,
            "showPorts": false,
            "streaming": false,
            "subject": null,
            "selected": false,
            "expanded": false,
            "group": -55,
            "inputApplicationName": "",
            "outputApplicationName": "",
            "exitApplicationName": "",
            "inputApplicationType": "None",
            "outputApplicationType": "None",
            "exitApplicationType": "None",
            "inputPorts": [
                {
                    "Id": "ccbc81df-d3e7-450d-84c1-62960529d4e4",
                    "IdText": "T-L"
                }
            ],
            "outputPorts": [
                {
                    "Id": "8fdbd398-1076-433d-a691-611ca915beb0",
                    "IdText": "B-T"
                }
            ],
            "inputLocalPorts": [],
            "outputLocalPorts": [],
            "inputAppFields": [],
            "outputAppFields": [],
            "fields": []
        },
        {
            "category": "Memory",
            "categoryType": "Data",
            "isData": false,
            "isGroup": false,
            "canHaveInputs": true,
            "canHaveOutputs": true,
            "color": "#394BB2",
            "drawOrderHint": 0,
            "key": -13,
            "text": "Image",
            "description": "",
            "x": 1342,
            "y": 380,
            "width": 200,
            "height": 200,
            "collapsed": false,
            "showPorts": false,
            "streaming": false,
            "subject": null,
            "selected": false,
            "expanded": false,
            "group": -55,
            "inputApplicationName": "",
            "outputApplicationName": "",
            "exitApplicationName": "",
            "inputApplicationType": "None",
            "outputApplicationType": "None",
            "exitApplicationType": "None",
            "inputPorts": [
                {
                    "Id": "2079408e-2fdf-41bd-84da-f3a85b9c0c53",
                    "IdText": "B-T"
                }
            ],
            "outputPorts": [
                {
                    "Id": "02c61496-302b-4802-a331-a3ffa5fafbb8",
                    "IdText": "B-T"
                }
            ],
            "inputLocalPorts": [],
            "outputLocalPorts": [],
            "inputAppFields": [],
            "outputAppFields": [],
            "fields": []
        },
        {
            "category": "Comment",
            "categoryType": "Other",
            "isData": false,
            "isGroup": false,
            "canHaveInputs": false,
            "canHaveOutputs": false,
            "color": "#799938",
            "drawOrderHint": 0,
            "key": -35,
            "text": "",
            "description": "",
            "x": 300,
            "y": 473,
            "width": 200,
            "height": 200,
            "collapsed": false,
            "showPorts": false,
            "streaming": false,
            "subject": null,
            "selected": false,
            "expanded": false,
            "inputApplicationName": "",
            "outputApplicationName": "",
            "exitApplicationName": "",
            "inputApplicationType": "None",
            "outputApplicationType": "None",
            "exitApplicationType": "None",
            "inputPorts": [],
            "outputPorts": [],
            "inputLocalPorts": [],
            "outputLocalPorts": [],
            "inputAppFields": [],
            "outputAppFields": [],
            "fields": [
                {
                    "text": "Comment",
                    "name": "comment",
                    "value": "What we are doing here is:\n* Facetted data reduction \n(spectral line, no LSM update\nparallel in facet & sub-band) \n* with DDE calibration and \n* uv-model subtraction\n-- Now gather facet before sub-band\n-- DQA 1-3 added",
                    "description": "The text value of the comment"
                }
            ]
        },
        {
            "category": "Memory",
            "categoryType": "Data",
            "isData": false,
            "isGroup": false,
            "canHaveInputs": true,
            "canHaveOutputs": true,
            "color": "#394BB2",
            "drawOrderHint": 0,
            "key": -37,
            "text": "  Default \nDDE Gains",
            "description": "",
            "x": 400,
            "y": 936,
            "width": 200,
            "height": 200,
            "collapsed": false,
            "showPorts": false,
            "streaming": false,
            "subject": null,
            "selected": false,
            "expanded": false,
            "inputApplicationName": "",
            "outputApplicationName": "",
            "exitApplicationName": "",
            "inputApplicationType": "None",
            "outputApplicationType": "None",
            "exitApplicationType": "None",
            "inputPorts": [],
            "outputPorts": [
                {
                    "Id": "d5e69120-7334-4cc0-b07e-c47924dcdc03",
                    "IdText": "R-L"
                }
            ],
            "inputLocalPorts": [],
            "outputLocalPorts": [],
            "inputAppFields": [],
            "outputAppFields": [],
            "fields": []
        },
        {
            "category": "Memory",
            "categoryType": "Data",
            "isData": false,
            "isGroup": false,
            "canHaveInputs": true,
            "canHaveOutputs": true,
            "color": "#394BB2",
            "drawOrderHint": 0,
            "key": -49,
            "text": "Flag \nDatabase",
            "description": "",
            "x": 1316,
            "y": 511,
            "width": 200,
            "height": 200,
            "collapsed": false,
            "showPorts": false,
            "streaming": false,
            "subject": null,
            "selected": false,
            "expanded": false,
            "inputApplicationName": "",
            "outputApplicationName": "",
            "exitApplicationName": "",
            "inputApplicationType": "None",
            "outputApplicationType": "None",
            "exitApplicationType": "None",
            "inputPorts": [
                {
                    "Id": "9d1dd3f3-8eea-45b6-921a-f0f64a6cd81c",
                    "IdText": "R-R"
                },
                {
                    "Id": "67eb763a-a102-4ec1-896b-d9e041616834",
                    "IdText": "B-L"
                },
                {
                    "Id": "fc4fc650-ced8-440b-a048-8adb0797e0de",
                    "IdText": "R-B"
                }
            ],
            "outputPorts": [
                {
                    "Id": "7cd9aaa6-4469-458e-befb-f5e18137b854",
                    "IdText": "T-L"
                }
            ],
            "inputLocalPorts": [],
            "outputLocalPorts": [],
            "inputAppFields": [],
            "outputAppFields": [],
            "fields": []
        },
        {
            "category": "GroupBy",
            "categoryType": "Group",
            "isData": false,
            "isGroup": true,
            "canHaveInputs": true,
            "canHaveOutputs": true,
            "color": "#7F8C8D",
            "drawOrderHint": 0,
            "key": -53,
            "text": "Group By Subband",
            "description": "",
            "x": 1556,
            "y": 691,
            "width": 200,
            "height": 200,
            "collapsed": false,
            "showPorts": false,
            "streaming": false,
            "subject": null,
            "selected": false,
            "expanded": false,
            "inputApplicationName": "",
            "outputApplicationName": "",
            "exitApplicationName": "",
            "inputApplicationType": "None",
            "outputApplicationType": "None",
            "exitApplicationType": "None",
            "inputPorts": [
                {
                    "Id": "eaa7f5e9-c1bd-4e43-b617-7946875ab2a6",
                    "IdText": "B-T"
                }
            ],
            "outputPorts": [],
            "inputLocalPorts": [],
            "outputLocalPorts": [],
            "inputAppFields": [],
            "outputAppFields": [],
            "fields": []
        },
        {
            "category": "Comment",
            "categoryType": "Other",
            "isData": false,
            "isGroup": false,
            "canHaveInputs": false,
            "canHaveOutputs": false,
            "color": "#799938",
            "drawOrderHint": 0,
            "key": -57,
            "text": "",
            "description": "",
            "x": 1618,
            "y": 672,
            "width": 200,
            "height": 200,
            "collapsed": false,
            "showPorts": false,
            "streaming": false,
            "subject": null,
            "selected": false,
            "expanded": false,
            "group": -53,
            "inputApplicationName": "",
            "outputApplicationName": "",
            "exitApplicationName": "",
            "inputApplicationType": "None",
            "outputApplicationType": "None",
            "exitApplicationType": "None",
            "inputPorts": [],
            "outputPorts": [],
            "inputLocalPorts": [],
            "outputLocalPorts": [],
            "inputAppFields": [],
            "outputAppFields": [],
            "fields": [
                {
                    "text": "Comment",
                    "name": "comment",
                    "value": "images in each grp \nhave the same \nsubband but from\n all facets",
                    "description": "The text value of the comment"
                }
            ]
        },
        {
            "category": "Gather",
            "categoryType": "Group",
            "isData": false,
            "isGroup": true,
            "canHaveInputs": true,
            "canHaveOutputs": true,
            "color": "#D35400",
            "drawOrderHint": 0,
            "key": -54,
            "text": "Gather Subband",
            "description": "",
            "x": 1401,
            "y": 907,
            "width": 200,
            "height": 200,
            "collapsed": false,
            "showPorts": false,
            "streaming": false,
            "subject": null,
            "selected": false,
            "expanded": false,
            "inputApplicationName": "",
            "outputApplicationName": "",
            "exitApplicationName": "",
            "inputApplicationType": "None",
            "outputApplicationType": "None",
            "exitApplicationType": "None",
            "inputPorts": [
                {
                    "Id": "3de7a545-de1d-4ba1-8fdf-5f5bb4cc7122",
                    "IdText": "B-T"
                }
            ],
            "outputPorts": [],
            "inputLocalPorts": [],
            "outputLocalPorts": [],
            "inputAppFields": [],
            "outputAppFields": [],
            "fields": [
                {
                    "text": "Number of inputs",
                    "name": "num_of_inputs",
                    "value": "1",
                    "description": ""
                },
                {
                    "text": "Gather Axis",
                    "name": "gather_axis",
                    "value": "",
                    "description": ""
                }
            ]
        },
        {
            "category": "GroupBy",
            "categoryType": "Group",
            "isData": false,
            "isGroup": true,
            "canHaveInputs": true,
            "canHaveOutputs": true,
            "color": "#7F8C8D",
            "drawOrderHint": 0,
            "key": -55,
            "text": "Group By Subband_Facet",
            "description": "",
            "x": 1434,
            "y": 340,
            "width": 200,
            "height": 200,
            "collapsed": false,
            "showPorts": false,
            "streaming": false,
            "subject": null,
            "selected": false,
            "expanded": false,
            "inputApplicationName": "",
            "outputApplicationName": "",
            "exitApplicationName": "",
            "inputApplicationType": "None",
            "outputApplicationType": "None",
            "exitApplicationType": "None",
            "inputPorts": [
                {
                    "Id": "e76e21d3-1edd-414a-9448-b57ad70ba153",
                    "IdText": "R-T"
                }
            ],
            "outputPorts": [],
            "inputLocalPorts": [],
            "outputLocalPorts": [],
            "inputAppFields": [],
            "outputAppFields": [],
            "fields": []
        },
        {
            "category": "Comment",
            "categoryType": "Other",
            "isData": false,
            "isGroup": false,
            "canHaveInputs": false,
            "canHaveOutputs": false,
            "color": "#799938",
            "drawOrderHint": 0,
            "key": -56,
            "text": "",
            "description": "",
            "x": 1489,
            "y": 336,
            "width": 200,
            "height": 200,
            "collapsed": false,
            "showPorts": false,
            "streaming": false,
            "subject": null,
            "selected": false,
            "expanded": false,
            "group": -55,
            "inputApplicationName": "",
            "outputApplicationName": "",
            "exitApplicationName": "",
            "inputApplicationType": "None",
            "outputApplicationType": "None",
            "exitApplicationType": "None",
            "inputPorts": [],
            "outputPorts": [],
            "inputLocalPorts": [],
            "outputLocalPorts": [],
            "inputAppFields": [],
            "outputAppFields": [],
            "fields": [
                {
                    "text": "Comment",
                    "name": "comment",
                    "value": "MS data in each grp \nbelong to the same \n[subband AND facet]\nbut from all days",
                    "description": "The text value of the comment"
                }
            ]
        },
        {
            "category": "Comment",
            "categoryType": "Other",
            "isData": false,
            "isGroup": false,
            "canHaveInputs": false,
            "canHaveOutputs": false,
            "color": "#799938",
            "drawOrderHint": 0,
            "key": -58,
            "text": "",
            "description": "",
            "x": 720,
            "y": 340,
            "width": 200,
            "height": 200,
            "collapsed": false,
            "showPorts": false,
            "streaming": false,
            "subject": null,
            "selected": false,
            "expanded": false,
            "group": -9,
            "inputApplicationName": "",
            "outputApplicationName": "",
            "exitApplicationName": "",
            "inputApplicationType": "None",
            "outputApplicationType": "None",
            "exitApplicationType": "None",
            "inputPorts": [],
            "outputPorts": [],
            "inputLocalPorts": [],
            "outputLocalPorts": [],
            "inputAppFields": [],
            "outputAppFields": [],
            "fields": [
                {
                    "text": "Comment",
                    "name": "comment",
                    "value": "Potential scatter in time. Not used",
                    "description": "The text value of the comment"
                }
            ]
        },
        {
            "category": "Comment",
            "categoryType": "Other",
            "isData": false,
            "isGroup": false,
            "canHaveInputs": false,
            "canHaveOutputs": false,
            "color": "#799938",
            "drawOrderHint": 0,
            "key": -59,
            "text": "",
            "description": "",
            "x": 927,
            "y": 649,
            "width": 200,
            "height": 200,
            "collapsed": false,
            "showPorts": false,
            "streaming": false,
            "subject": null,
            "selected": false,
            "expanded": false,
            "group": -8,
            "inputApplicationName": "",
            "outputApplicationName": "",
            "exitApplicationName": "",
            "inputApplicationType": "None",
            "outputApplicationType": "None",
            "exitApplicationType": "None",
            "inputPorts": [],
            "outputPorts": [],
            "inputLocalPorts": [],
            "outputLocalPorts": [],
            "inputAppFields": [],
            "outputAppFields": [],
            "fields": [
                {
                    "text": "Comment",
                    "name": "comment",
                    "value": "DQA2 for spectral line. Continuum _will_ split on (a few) subbands, but not require DQA2",
                    "description": "The text value of the comment"
                }
            ]
        },
        {
            "category": "Comment",
            "categoryType": "Other",
            "isData": false,
            "isGroup": false,
            "canHaveInputs": false,
            "canHaveOutputs": false,
            "color": "#799938",
            "drawOrderHint": 0,
            "key": -60,
            "text": "",
            "description": "",
            "x": 1506,
            "y": 100,
            "width": 200,
            "height": 200,
            "collapsed": false,
            "showPorts": false,
            "streaming": false,
            "subject": null,
            "selected": false,
            "expanded": false,
            "inputApplicationName": "",
            "outputApplicationName": "",
            "exitApplicationName": "",
            "inputApplicationType": "None",
            "outputApplicationType": "None",
            "exitApplicationType": "None",
            "inputPorts": [],
            "outputPorts": [],
            "inputLocalPorts": [],
            "outputLocalPorts": [],
            "inputAppFields": [],
            "outputAppFields": [],
            "fields": [
                {
                    "text": "Comment",
                    "name": "comment",
                    "value": "Place to look at the data quantities. We will explore the number of drops in this frame work.",
                    "description": "The text value of the comment"
                }
            ]
        }
    ],
    "linkDataArray": [
        {
            "from": -25,
            "fromPort": "56bfb1e9-c2f4-4c42-b8fa-95ef0c8ce952",
            "to": -23,
            "toPort": "9a18f403-c27f-48e5-8d08-793c6323cd26"
        },
        {
            "from": -26,
            "fromPort": "aadcb9b2-a522-4600-95dd-72c515291280",
            "to": -19,
            "toPort": "42bdb179-d669-4a37-a923-d318e04653da"
        },
        {
            "from": -31,
            "fromPort": "33c08a20-d1bb-4c70-b8e6-c0549227e56c",
            "to": -22,
            "toPort": "573ddd59-f17c-497f-9531-709306944c0d"
        },
        {
            "from": -31,
            "fromPort": "4c60aec6-45fd-4c63-b118-7c1585523f16",
            "to": -23,
            "toPort": "c250f06b-8a0f-4ed4-ae21-e4bf23030aae"
        },
        {
            "from": -30,
            "fromPort": "e0a78bb7-3714-4e37-9103-1da2c6eef46f",
            "to": -24,
            "toPort": "707d994c-5799-4da5-a45d-c5965dc7a6b7"
        },
        {
            "from": -40,
            "fromPort": "7ed4e7eb-5177-4522-b897-ebfef2fc3de7",
            "to": -41,
            "toPort": "520a2196-2f14-4c8a-a5b3-0e5c2eb2018b"
        },
        {
            "from": -41,
            "fromPort": "4b5645e9-82e9-4730-83a3-d200ebd44369",
            "to": -26,
            "toPort": "543ae37b-8bf0-4309-96f0-88e57f8ad67a"
        },
        {
            "from": -19,
            "fromPort": "eb180926-b220-47b5-bfc4-789cdfd47507",
            "to": -36,
            "toPort": "df33d41d-7af2-4c17-95f6-7c00cd2b399b"
        },
        {
            "from": -36,
            "fromPort": "023f6598-38f7-4552-a2db-26a41fe67793",
            "to": -31,
            "toPort": "dd4d0ffe-f42e-4f24-9f6c-43a2530f7576"
        },
        {
            "from": -23,
            "fromPort": "6ceb3641-54ea-4829-a516-bffa9e90db55",
            "to": -30,
            "toPort": "c0f3a2fd-ad74-456f-9363-8839e6b9bb8d"
        },
        {
            "from": -22,
            "fromPort": "6530a415-9dab-48a9-bb34-ed12cb5f8bcf",
            "to": -25,
            "toPort": "7206f669-064b-4625-94de-7782663aa060"
        },
        {
            "from": -24,
            "fromPort": "4bedb5fa-819c-4595-889a-14dd08ce05c2",
            "to": -33,
            "toPort": "fe53fefd-cf27-4004-ab9a-3ce80a45ce24"
        },
        {
            "from": -33,
            "fromPort": "a19f49ef-9d52-4974-8525-b78c8cb72c75",
            "to": -46,
            "toPort": "3c40ecee-15a1-4875-9149-549dc9d93eb7"
        },
        {
            "from": -46,
            "fromPort": "9ce794e0-3910-4f7b-bc04-4fda0852fa7c",
            "to": -47,
            "toPort": "c099f2fb-aff1-470e-8cab-5fceea0e147e"
        },
        {
            "from": -47,
            "fromPort": "2681bcec-02eb-4455-ba41-89db4148fe4d",
            "to": -52,
            "toPort": "14ef7119-530b-439d-ae4d-4672303353d3"
        },
        {
            "from": -44,
            "fromPort": "2e431728-6b0a-43df-ba21-b20214c6ae2f",
            "to": -45,
            "toPort": "6e60b195-7d68-4cbd-ba5c-716e30a78156"
        },
        {
            "from": -38,
            "fromPort": "89cc2860-3056-4564-b935-60c155c8190e",
            "to": -48,
            "toPort": "71b84463-33ea-4070-864d-e398cddea6d2"
        },
        {
            "from": -45,
            "fromPort": "d8c1b5cc-6d09-427b-91a9-1dc6e6b05af9",
            "to": -51,
            "toPort": "661e61a6-74b9-46e4-b473-50cec9ef593b"
        },
        {
            "from": -48,
            "fromPort": "321d9bf0-b925-43f2-8fdb-3685b7cd6bcd",
            "to": -40,
            "toPort": "fd05f294-e1bd-466e-9f4f-ece71b48a05d"
        },
        {
            "from": -27,
            "fromPort": "3d70ba08-38d3-48cb-bd16-f97dcbc562b1",
            "to": -2,
            "toPort": "91bda289-61d1-46c6-961a-6d19a379cf11"
        },
        {
            "from": -2,
            "fromPort": "de4c6c15-d342-4d3f-ac61-ec8f04d2f3ed",
            "to": -3,
            "toPort": "ea142eaa-2c29-409c-9851-18b2748d5cb8"
        },
        {
            "from": -3,
            "fromPort": "5b0ef79a-0256-4e17-ad8e-0641f5ed5688",
            "to": -5,
            "toPort": "ae73c259-347c-4a5f-90e4-c3618296dcaf"
        },
        {
            "from": -5,
            "fromPort": "f743ddd6-f5b6-446c-8e36-3d33d9cac644",
            "to": -38,
            "toPort": "3d88a9e4-7a5a-4a72-a787-fab11946fb15"
        },
        {
            "from": -42,
            "fromPort": "ab4d6336-ae74-497f-abfe-bcdfe533c7d8",
            "to": -43,
            "toPort": "4f8b0a13-a70d-4394-8602-c7e6d8a3216b"
        },
        {
            "from": -43,
            "fromPort": "3e800c2f-56dd-4f0d-9130-61854a217af6",
            "to": -50,
            "toPort": "edb4b855-8333-48ff-8b5d-c885e77708b8"
        },
        {
            "from": -21,
            "fromPort": "776b6f14-06b5-47c3-bc7d-d118c49ff7eb",
            "to": -19,
            "toPort": "3ff89eac-10a7-4781-a423-a2fe977a013e"
        },
        {
            "from": -28,
            "fromPort": "8725d727-97ee-46b0-9c37-483d34458524",
            "to": -29,
            "toPort": "d54e0d42-d8d9-41be-bc8b-4e5c97334540"
        },
        {
            "from": -39,
            "fromPort": "c545e4a6-22a9-44e6-9c1a-fd45842487c6",
            "to": -18,
            "toPort": "7624d0f0-651f-4f38-8faf-295f6cc94453"
        },
        {
            "from": -18,
            "fromPort": "5c93343e-434b-4d60-8dda-c4817f6dd51c",
            "to": -32,
            "toPort": "dc549a78-75f1-472c-ba09-6c172e77757d"
        },
        {
            "from": -16,
            "fromPort": "8fdbd398-1076-433d-a691-611ca915beb0",
            "to": -13,
            "toPort": "2079408e-2fdf-41bd-84da-f3a85b9c0c53"
        },
        {
            "from": -37,
            "fromPort": "d5e69120-7334-4cc0-b07e-c47924dcdc03",
            "to": -23,
            "toPort": "829bbb17-7e48-4e6a-94ab-371eade864fe"
        },
        {
            "from": -49,
            "fromPort": "7cd9aaa6-4469-458e-befb-f5e18137b854",
            "to": -16,
            "toPort": "ccbc81df-d3e7-450d-84c1-62960529d4e4"
        },
        {
            "from": -50,
            "fromPort": "e99693ca-b957-4dbf-a252-e2987a8785f2",
            "to": -49,
            "toPort": "9d1dd3f3-8eea-45b6-921a-f0f64a6cd81c"
        },
        {
            "from": -51,
            "fromPort": "2b700f63-b1ab-4545-a97f-66dd4dcf71f6",
            "to": -49,
            "toPort": "67eb763a-a102-4ec1-896b-d9e041616834"
        },
        {
            "from": -52,
            "fromPort": "c3ef48a9-ca32-471c-8b46-6fd3c3cd11a5",
            "to": -49,
            "toPort": "fc4fc650-ced8-440b-a048-8adb0797e0de"
        },
        {
            "from": -13,
            "fromPort": "02c61496-302b-4802-a331-a3ffa5fafbb8",
            "to": -53,
            "toPort": "eaa7f5e9-c1bd-4e43-b617-7946875ab2a6"
        },
        {
            "from": -29,
            "fromPort": "2e1d2659-b7e3-4ebd-880f-41f2c8f9b647",
            "to": -54,
            "toPort": "3de7a545-de1d-4ba1-8fdf-5f5bb4cc7122"
        },
        {
            "from": -33,
            "fromPort": "94b57bdb-d84b-4ad7-9a1f-83f2b20e8c7f",
            "to": -55,
            "toPort": "e76e21d3-1edd-414a-9448-b57ad70ba153"
        },
        {
            "from": -3,
            "fromPort": "1a64618c-952d-43c8-812e-6d6a117e3451",
            "to": -42,
            "toPort": "7a94f78f-b14b-47b9-8ea4-773e10db2720"
        },
        {
            "from": -38,
            "fromPort": "3dfe8fb4-0baf-405f-8634-9520f8a573d7",
            "to": -44,
            "toPort": "ea40f507-667d-4a5b-979e-614dae226dc4"
        }
    ]
}